Workbook

Sheet Sheet1

Sheet Sheet3
S1: EXCESSO | T1: ARROZ | U1: FEIJAO | V1: MILHO | W1: TOTAL | AE1: =+V2+#REF! -> #REF!
E2: ARROZ | I2: FEIJAO | M2: MILHO | Q2: TOTAL | S2: SOFALA | T2: 0 | U2: 4935 | V2: 73762.5 | W2: 78697.5
B3: Column Labels
B4: Arroz | F4: Feijão | J4: Milho | N4: Total Sum of NOVA QUANTIDADE A ENTREGAR | O4: Total Sum of VAR VS PLAN ANTERIOR | P4: Total Sum of QUANTIDADE ENTREGUE | Q4: Total Sum of QUANTIDADE ENTREGUE +/-
A5: Row Labels | B5: Sum of NOVA QUANTIDADE A ENTREGAR | C5: Sum of VAR VS PLAN ANTERIOR | D5: Sum of QUANTIDADE ENTREGUE | E5: Sum of QUANTIDADE ENTREGUE +/- | F5: Sum of NOVA QUANTIDADE A ENTREGAR | G5: Sum of VAR VS PLAN ANTERIOR | H5: Sum of QUANTIDADE ENTREGUE | I5: Sum of QUANTIDADE ENTREGUE +/- | J5: Sum of NOVA QUANTIDADE A ENTREGAR | K5: Sum of VAR VS PLAN ANTERIOR | L5: Sum of QUANTIDADE ENTREGUE | M5: Sum of QUANTIDADE ENTREGUE +/-
A6: Gaza | B6: 437800 | C6: 0 | D6: 28800 | E6: -409000 | F6: 1131480 | G6: 0 | H6: 50565 | I6: -1080915 | J6: 833450 | K6: 0 | L6: 763809 | M6: -69641 | N6: 2402730 | O6: 0 | P6: 843174 | Q6: -1559556
A7: Manica | B7: 0 | C7: 0 | D7: 0 | E7: 0 | F7: 35850 | G7: -77460 | H7: 0 | I7: -35850 | J7: 29875 | K7: -64550 | L7: 2000 | M7: -27875 | N7: 65725 | O7: -142010 | P7: 2000 | Q7: -63725
A8: Maputo | B8: 98500 | C8: 0 | D8: 0 | E8: -98500 | F8: 268500 | G8: 0 | H8: 11490 | I8: -257010 | J8: 199125 | K8: 0 | L8: 172727 | M8: -26398 | N8: 566125 | O8: 0 | P8: 184217 | Q8: -381908
A9: Sofala | B9: 366550 | C9: -198800 | D9: 0 | E9: -366550 | F9: 317115 | G9: -260205 | H9: 62385 | I9: -254730 | J9: 214800 | K9: -124962.5 | L9: 185526 | M9: -29274 | N9: 898465 | O9: -583967.5 | P9: 247911 | Q9: -650554
A10: Beira | B10: 7500 | C10: -2300 | D10: 0 | E10: -7500 | F10: 2250 | G10: -690 | H10: 0 | I10: -2250 | N10: 9750 | O10: -2990 | P10: 0 | Q10: -9750
A11: Buzi | B11: 210500 | C11: -233300 | D11: 0 | E11: -210500 | F11: 104400 | G11: -109380 | H11: 9555 | I11: -94845 | J11: 65925 | K11: -1275 | L11: 59288 | M11: -6637 | N11: 380825 | O11: -343955 | P11: 68843 | Q11: -311982
A12: Caia | B12: 42650 | C12: -31300 | D12: 0 | E12: -42650 | F12: 34965 | G12: -8490 | H12: 30000 | I12: -4965 | J12: 18475 | K12: 750 | L12: 0 | M12: -18475 | N12: 96090 | O12: -39040 | P12: 30000 | Q12: -66090
A13: Chemba | B13: 4450 | C13: -32200 | D13: 0 | E13: -4450 | F13: 33570 | G13: -60735 | H13: 0 | I13: -33570 | J13: 26862.5 | K13: -42562.5 | L13: 29999 | M13: 3136.5 | N13: 64882.5 | O13: -135497.5 | P13: 29999 | Q13: -34883.5
A14: Chibabava | F14: 9885 | G14: 4035 | H14: 0 | I14: -9885 | J14: 8237.5 | K14: 3362.5 | L14: 0 | M14: -8237.5 | N14: 18122.5 | O14: 7397.5 | P14: 0 | Q14: -18122.5
A15: Dondo | B15: 19300 | C15: 19300 | D15: 0 | E15: -19300 | F15: 5790 | G15: -11625 | H15: 0 | I15: -5790 | J15: 0 | K15: -14512.5 | L15: 0 | M15: 0 | N15: 25090 | O15: -6837.5 | P15: 0 | Q15: -25090
A16: Gorongosa | B16: 0 | C16: 0 | D16: 0 | E16: 0 | F16: 14220 | G16: 8100 | H16: 5850 | I16: -8370 | J16: 11850 | K16: 6750 | L16: 5101 | M16: -6749 | N16: 26070 | O16: 14850 | P16: 10951 | Q16: -15119
A17: Machanga | B17: 4550 | C17: 4550 | D17: 0 | E17: -4550 | F17: 52335 | G17: -33120 | H17: 0 | I17: -52335 | J17: 42475 | K17: -28737.5 | L17: 35951 | M17: -6524 | N17: 99360 | O17: -57307.5 | P17: 35951 | Q17: -63409
A18: Marromeu | B18: 17600 | C18: 17600 | D18: 0 | E18: -17600 | F18: 7575 | G18: 180 | H18: 0 | I18: -7575 | J18: 1912.5 | K18: -4250 | L18: 0 | M18: -1912.5 | N18: 27087.5 | O18: 13530 | P18: 0 | Q18: -27087.5
A19: Muanza | B19: 25000 | C19: 25000 | D19: 0 | E19: -25000 | F19: 14685 | G19: -8760 | H19: 0 | I19: -14685 | J19: 5987.5 | K19: -13550 | L19: 0 | M19: -5987.5 | N19: 45672.5 | O19: 2690 | P19: 0 | Q19: -45672.5
A20: Nhamatanda | B20: 35000 | C20: 33850 | D20: 0 | E20: -35000 | F20: 37440 | G20: -39720 | H20: 16980 | I20: -20460 | J20: 33075 | K20: -30937.5 | L20: 55187 | M20: 22112 | N20: 105515 | O20: -36807.5 | P20: 72167 | Q20: -33348
A21: Tete | B21: 1000 | C21: -61900 | D21: 0 | E21: -1000 | F21: 58515 | G21: -51540 | H21: 0 | I21: -58515 | J21: 48512.5 | K21: -27475 | L21: 27451 | M21: -21061.5 | N21: 108027.5 | O21: -140915 | P21: 27451 | Q21: -80576.5
A22: Zambezia | B22: 84500 | C22: -124250 | D22: 0 | E22: -84500 | F22: 102180 | G22: -77520 | H22: 0 | I22: -102180 | J22: 64025 | K22: -33550 | L22: 0 | M22: -64025 | N22: 250705 | O22: -235320 | P22: 0 | Q22: -250705
A23: Grand Total | B23: 988350 | C23: -384950 | D23: 28800 | E23: -959550 | F23: 1913640 | G23: -466725 | H23: 124440 | I23: -1789200 | J23: 1389787.5 | K23: -250537.5 | L23: 1151513 | M23: -238274.5 | N23: 4291777.5 | O23: -1102212.5 | P23: 1304753 | Q23: -2987024.5
B26: 877700 | C26: -495600 | D26: 28800 | E26: -848900 | F26: 1823640 | G26: -556725 | H26: 124440 | I26: -1699200 | J26: 1300275 | K26: -340050 | L26: 1151513 | M26: -148752 | Q26: -2696862
B27: =+B23-B26 -> 110650 | C27: =+C23-C26 -> 110650 | D27: =+D23-D26 -> 0 | E27: =+E23-E26 -> -110650 | F27: =+F23-F26 -> 90000 | G27: =+G23-G26 -> 90000 | H27: =+H23-H26 -> 0 | I27: =+I23-I26 -> -90000 | ... P27: =+P23-P26 -> 1304753 | Q27: =+Q26-Q23 -> 290162.5

Sheet Planeamento Adicional
A1: Data | B1: Referencia | C1: codigo serviço | D1: Tipo | E1: Codigo Cliente | F1: Nº Volume novo | G1: Peso do Volume Kg | H1: NOVA QUANTIDADE A ENTREGAR | I1: VAR VS PLAN ANTERIOR | J1: Qtd kit1 | K1: Qtd kit2 | L1: Altura | M1: Largura | N1: Comprimento | O1: Nome Origem | P1: Morada Origem | Q1: Artigo | R1: Nº Fornecedor | S1: Cod Origem ( NUIT) | T1: Código Postal Origem | U1: Cod Destino ( NUIT) | V1: Nome Destino | W1: Morada Destino (Provincia) | X1: Distrito | Y1: Posto Administrativo | Z1: Localidade | AA1: Povoado | AB1: Local de Treinamento | AC1: Total de Kits por Povoado | AD1: Localidade Destino Destino | AE1: Código Postal Destino Destino | AF1: Nome do Extensionista | AG1: Num Contacto Destino (Contacto do extensionista) | AH1: Nome do Supervisor | AI1: Contacto do Supervisor | AJ1: Observações | AK1: CDT | AL1: Valor | AM1: Plano Facturaçao | AO1: Agregador | AP1: Proforma | AQ1: SDAE | AR1: Supervisor | AS1: custo unitario | AT1: Custo | AU1: preco unitario | AV1: Venda | AW1: Data de Recebimento | AX1: Data de Pagamento | AY1: Garantias | AZ1: Stock p/fornecer | BA1: Variação | BB1: Qtd Entregue (Finalizado) | BC1: Qtd Em Trânsito | BD1: Qtd Criado (ajustável) | BE1: QUANTIDADE ENTREGUE | BF1: QUANTIDADE ENTREGUE +/- | BG1: Estado Entrega | BH1: Extensionista Count | BL1: Qtd Actualizada | BM1: VAR | BN1: Extensionist_ID | BO1: Tipo de Feijão
A2: 46114 | B2: Feijão | F2: 75 | G2: 75 | H2: 0 | Q2: MXIXFEIJAOKG | U2: 2601050 | V2: Abdulcadre Antonio | W2: Zambezia | X2: A.Molocue | Y2: Chapala | AF2: Abdulcadre Antonio | AG2: 873020203 | AH2: Jacob Manuel | AI2: 865421928 | AM2: 260001 | BA2: -75 | BE2: =+BB2+BC2 -> 0 | BF2: =+BE2-H2 -> 0 | BG2: Sem registo | BH2: =+VLOOKUP(AF2,Sheet4!A:A,1,FALSE) -> #N/A | BL2: 0 | BM2: =+H2+-BL2 -> 0 | BN2: 0601-0001 | BO2: Vulgar
A3: 46114 | B3: Emamectin | F3: 5 | G3: 2.5 | H3: 0 | Q3: AGRIFEMMA01L | U3: 2601050 | V3: Abdulcadre Antonio | W3: Zambezia | X3: A.Molocue | Y3: Chapala | AF3: Abdulcadre Antonio | AG3: 873020203 | AH3: Jacob Manuel | AI3: 865421928 | AM3: 260001 | BA3: -5 | BE3: =+BB3+BC3 -> 0 | BF3: =+BE3-H3 -> 0 | BG3: Sem registo | BH3: =+VLOOKUP(AF3,Sheet4!A:A,1,FALSE) -> #N/A | BL3: 0 | BM3: =+H3+-BL3 -> 0 | BN3: 0601-0001
A4: 46114 | B4: Sacos Hermeticos | F4: 100 | G4: 100 | H4: 0 | Q4: SUSSACO | U4: 2601050 | V4: Abdulcadre Antonio | W4: Zambezia | X4: A.Molocue | Y4: Chapala | AF4: Abdulcadre Antonio | AG4: 873020203 | AH4: Jacob Manuel | AI4: 865421928 | AM4: 260001 | BA4: -100 | BE4: =+BB4+BC4 -> 0 | BF4: =+BE4-H4 -> 0 | BG4: Sem registo | BH4: =+VLOOKUP(AF4,Sheet4!A:A,1,FALSE) -> #N/A | BL4: 0 | BM4: =+H4+-BL4 -> 0 | BN4: 0601-0001
A5: 46114 | B5: Imadocloprid | F5: 4 | G5: 2 | H5: 0 | Q5: AGRIMIDACLORP1L | U5: 2601050 | V5: Abdulcadre Antonio | W5: Zambezia | X5: A.Molocue | Y5: Chapala | AF5: Abdulcadre Antonio | AG5: 873020203 | AH5: Jacob Manuel | AI5: 865421928 | AM5: 260001 | BA5: -4 | BE5: =+BB5+BC5 -> 0 | BF5: =+BE5-H5 -> 0 | BG5: Sem registo | BH5: =+VLOOKUP(AF5,Sheet4!A:A,1,FALSE) -> #N/A | BL5: 0 | BM5: =+H5+-BL5 -> 0 | BN5: 0601-0001
A6: 46114 | B6: Milho | F6: 50 | G6: 50 | H6: 0 | J6: =H6/12.5 -> 0 | Q6: MXIXMILHOKG | U6: 2601050 | V6: Abdulcadre Antonio | W6: Zambezia | X6: A.Molocue | Y6: Chapala | AF6: Abdulcadre Antonio | AG6: 873020203 | AH6: Jacob Manuel | AI6: 865421928 | AM6: 260001 | BA6: -50 | BE6: =+BB6+BC6 -> 0 | BF6: =+BE6-H6 -> 0 | BG6: Sem registo | BH6: =+VLOOKUP(AF6,Sheet4!A:A,1,FALSE) -> #N/A | BL6: 0 | BM6: =+H6+-BL6 -> 0 | BN6: 0601-0001
A7: 46114 | B7: MCPA | F7: 3 | G7: 1.5 | H7: 0 | Q7: AGRIMHMCPA1L | U7: 2601050 | V7: Abdulcadre Antonio | W7: Zambezia | X7: A.Molocue | Y7: Chapala | AF7: Abdulcadre Antonio | AG7: 873020203 | AH7: Jacob Manuel | AI7: 865421928 | AM7: 260001 | BA7: -3 | BE7: =+BB7+BC7 -> 0 | BF7: =+BE7-H7 -> 0 | BG7: Sem registo | BH7: =+VLOOKUP(AF7,Sheet4!A:A,1,FALSE) -> #N/A | BL7: 0 | BM7: =+H7+-BL7 -> 0 | BN7: 0601-0001
A8: 46114 | B8: Arroz | F8: 50 | G8: 50 | H8: 0 | I8: =H8-G8 -> -50 | K8: =H8/50 -> 0 | Q8: MXIXARROZKG | U8: 2601050 | V8: Abdulcadre Antonio | W8: Zambezia | X8: A.Molocue | Y8: Chapala | AF8: Abdulcadre Antonio | AG8: 873020203 | AH8: Jacob Manuel | AI8: 865421928 | AM8: 260001 | BA8: -50 | BE8: =+BB8+BC8 -> 0 | BF8: =+BE8-H8 -> 0 | BG8: Sem registo | BH8: =+VLOOKUP(AF8,Sheet4!A:A,1,FALSE) -> #N/A | BL8: 0 | BM8: =+H8+-BL8 -> 0 | BN8: 0601-0001
A9: 46114 | B9: Feijão | F9: 1425 | G9: 1425 | H9: 315 | I9: =H9-G9 -> -1110 | Q9: MXIXFEIJAOKG | U9: 2601051 | V9: Abiba Paiva Luís Lundo | W9: Zambezia | X9: CHINDE | Y9: MATILDE | AF9: Abiba Paiva Luís Lundo | AG9: 877471047/845258221 | AH9: Victor Carlos Duarte Soromenho | AI9: 848973362 / 874800380 | AM9: 260001 | BA9: -1110 | BE9: =+BB9+BC9 -> 0 | BF9: =+BE9-H9 -> -315 | BG9: Sem registo | BH9: =+VLOOKUP(AF9,Sheet4!A:A,1,FALSE) -> #N/A | BL9: 315 | BM9: =+H9+-BL9 -> 0 | BN9: 0602-0001 | BO9: Vulgar
A10: 46114 | B10: Emamectin | F10: 95 | G10: 47.5 | H10: 21 | I10: =H10-G10 -> -26.5 | Q10: AGRIFEMMA01L | U10: 2601051 | V10: Abiba Paiva Luís Lundo | W10: Zambezia | X10: CHINDE | Y10: MATILDE | AF10: Abiba Paiva Luís Lundo | AG10: 877471047/845258221 | AH10: Victor Carlos Duarte Soromenho | AI10: 848973362 / 874800380 | AM10: 260001 | BA10: -74 | BE10: =+BB10+BC10 -> 0 | BF10: =+BE10-H10 -> -21 | BG10: Sem registo | BH10: =+VLOOKUP(AF10,Sheet4!A:A,1,FALSE) -> #N/A | BL10: 21 | BM10: =+H10+-BL10 -> 0 | BN10: 0602-0001
A11: 46114 | B11: Sacos Hermeticos | F11: 1900 | G11: 1900 | H11: 420 | I11: =H11-G11 -> -1480 | Q11: SUSSACO | U11: 2601051 | V11: Abiba Paiva Luís Lundo | W11: Zambezia | X11: CHINDE | Y11: MATILDE | AF11: Abiba Paiva Luís Lundo | AG11: 877471047/845258221 | AH11: Victor Carlos Duarte Soromenho | AI11: 848973362 / 874800380 | AM11: 260001 | BA11: -1480 | BE11: =+BB11+BC11 -> 0 | BF11: =+BE11-H11 -> -420 | BG11: Sem registo | BH11: =+VLOOKUP(AF11,Sheet4!A:A,1,FALSE) -> #N/A | BL11: 420 | BM11: =+H11+-BL11 -> 0 | BN11: 0602-0001
A12: 46114 | B12: Imadocloprid | F12: 76 | G12: 38 | H12: 18 | I12: =H12-G12 -> -20 | Q12: AGRIMIDACLORP1L | U12: 2601051 | V12: Abiba Paiva Luís Lundo | W12: Zambezia | X12: CHINDE | Y12: MATILDE | AF12: Abiba Paiva Luís Lundo | AG12: 877471047/845258221 | AH12: Victor Carlos Duarte Soromenho | AI12: 848973362 / 874800380 | AM12: 260001 | BA12: -58 | BE12: =+BB12+BC12 -> 0 | BF12: =+BE12-H12 -> -18 | BG12: Sem registo | BH12: =+VLOOKUP(AF12,Sheet4!A:A,1,FALSE) -> #N/A | BL12: 18 | BM12: =+H12+-BL12 -> 0 | BN12: 0602-0001
A13: 46114 | B13: Milho | F13: 950 | G13: 950 | H13: 225 | I13: =H13-G13 -> -725 | J13: =H13/12.5 -> 18 | Q13: MXIXMILHOKG | U13: 2601051 | V13: Abiba Paiva Luís Lundo | W13: Zambezia | X13: CHINDE | Y13: MATILDE | AF13: Abiba Paiva Luís Lundo | AG13: 877471047/845258221 | AH13: Victor Carlos Duarte Soromenho | AI13: 848973362 / 874800380 | AM13: 260001 | BA13: -725 | BE13: =+BB13+BC13 -> 0 | BF13: =+BE13-H13 -> -225 | BG13: Sem registo | BH13: =+VLOOKUP(AF13,Sheet4!A:A,1,FALSE) -> #N/A | BL13: 225 | BM13: =+H13+-BL13 -> 0 | BN13: 0602-0001
A14: 46114 | B14: MCPA | F14: 57 | G14: 28.5 | H14: 9 | I14: =H14-G14 -> -19.5 | Q14: AGRIMHMCPA1L | U14: 2601051 | V14: Abiba Paiva Luís Lundo | W14: Zambezia | X14: CHINDE | Y14: MATILDE | AF14: Abiba Paiva Luís Lundo | AG14: 877471047/845258221 | AH14: Victor Carlos Duarte Soromenho | AI14: 848973362 / 874800380 | AM14: 260001 | BA14: -48 | BE14: =+BB14+BC14 -> 0 | BF14: =+BE14-H14 -> -9 | BG14: Sem registo | BH14: =+VLOOKUP(AF14,Sheet4!A:A,1,FALSE) -> #N/A | BL14: 9 | BM14: =+H14+-BL14 -> 0 | BN14: 0602-0001
A15: 46114 | B15: Arroz | F15: 950 | G15: 950 | H15: 150 | I15: =H15-G15 -> -800 | K15: =H15/50 -> 3 | Q15: MXIXARROZKG | U15: 2601051 | V15: Abiba Paiva Luís Lundo | W15: Zambezia | X15: CHINDE | Y15: MATILDE | AF15: Abiba Paiva Luís Lundo | AG15: 877471047/845258221 | AH15: Victor Carlos Duarte Soromenho | AI15: 848973362 / 874800380 | AM15: 260001 | BA15: -800 | BE15: =+BB15+BC15 -> 0 | BF15: =+BE15-H15 -> -150 | BG15: Sem registo | BH15: =+VLOOKUP(AF15,Sheet4!A:A,1,FALSE) -> #N/A | BL15: 150 | BM15: =+H15+-BL15 -> 0 | BN15: 0602-0001
A16: 46114 | B16: Feijão | F16: 315 | G16: 315 | H16: 255 | I16: -60 | Q16: MXIXFEIJAOKG | U16: 2601052 | V16: Abílio Vilanculos | W16: Maputo | X16: MANHIÇA | Y16: Associação agrícola de Malhalhana | AF16: Abílio Vilanculos | AG16: 852314121 | AH16: Joaquim Arnaldo Muchanga | AI16: 847870520 | AM16: 260001 | BC16: 315 | BE16: =+BB16+BC16 -> 315 | BF16: =+BE16-H16 -> 60 | BG16: Entregue | BH16: =+VLOOKUP(AF16,Sheet4!A:A,1,FALSE) -> #N/A | BL16: 315 | BM16: =+H16+-BL16 -> -60 | BN16: 0303-0001 | BO16: Nhemba
A17: 46114 | B17: Feijão | F17: 375 | G17: 375 | H17: 300 | I17: -75 | Q17: MXIXFEIJAOKG | U17: 2601052 | V17: Abílio Vilanculos | W17: Maputo | X17: MANHIÇA | Y17: Associação de Balucuene | AF17: Abílio Vilanculos | AG17: 852314121 | AH17: Joaquim Arnaldo Muchanga | AI17: 847870520 | AM17: 260001 | BC17: 375 | BE17: =+BB17+BC17 -> 375 | BF17: =+BE17-H17 -> 75 | BG17: Entregue | BH17: =+VLOOKUP(AF17,Sheet4!A:A,1,FALSE) -> #N/A | BL17: 375 | BM17: =+H17+-BL17 -> -75 | BN17: 0303-0001 | BO17: Nhemba
A18: 46114 | B18: Feijão | F18: 135 | G18: 135 | H18: 105 | I18: -30 | Q18: MXIXFEIJAOKG | U18: 2601052 | V18: Abílio Vilanculos | W18: Maputo | X18: MANHIÇA | Y18: Associação de Chibucutso | AF18: Abílio Vilanculos | AG18: 852314121 | AH18: Joaquim Arnaldo Muchanga | AI18: 847870520 | AM18: 260001 | BD18: 135 | BE18: =+BB18+BC18 -> 0 | BF18: =+BE18-H18 -> -105 | BG18: Sem registo | BH18: =+VLOOKUP(AF18,Sheet4!A:A,1,FALSE) -> #N/A | BL18: 135 | BM18: =+H18+-BL18 -> -30 | BN18: 0303-0001 | BO18: Nhemba
A19: 46114 | B19: Feijão | F19: 870 | G19: 870 | H19: 705 | I19: -165 | Q19: MXIXFEIJAOKG | U19: 2601052 | V19: Abílio Vilanculos | W19: Maputo | X19: MANHIÇA | Y19: Associação DE Chirindzene | AF19: Abílio Vilanculos | AG19: 852314121 | AH19: Joaquim Arnaldo Muchanga | AI19: 847870520 | AM19: 260001 | BD19: 870 | BE19: =+BB19+BC19 -> 0 | BF19: =+BE19-H19 -> -705 | BG19: Sem registo | BH19: =+VLOOKUP(AF19,Sheet4!A:A,1,FALSE) -> #N/A | BL19: 870 | BM19: =+H19+-BL19 -> -165 | BN19: 0303-0001 | BO19: Nhemba
A20: 46114 | B20: Feijão | F20: 7545 | G20: 7545 | H20: 6075 | I20: -1470 | Q20: MXIXFEIJAOKG | U20: 2601052 | V20: Abílio Vilanculos | W20: Maputo | X20: MANHIÇA | Y20: Chirindzene | AF20: Abílio Vilanculos | AG20: 852314121 | AH20: Joaquim Arnaldo Muchanga | AI20: 847870520 | AM20: 260001 | BD20: 7545 | BE20: =+BB20+BC20 -> 0 | BF20: =+BE20-H20 -> -6075 | BG20: Sem registo | BH20: =+VLOOKUP(AF20,Sheet4!A:A,1,FALSE) -> #N/A | BL20: 7545 | BM20: =+H20+-BL20 -> -1470 | BN20: 0303-0001 | BO20: Nhemba
A21: 46114 | B21: Feijão | F21: 15 | G21: 15 | H21: 15 | I21: 0 | Q21: MXIXFEIJAOKG | U21: 2601052 | V21: Abílio Vilanculos | W21: Maputo | X21: MANHIÇA | Y21: Manhica-sede | AF21: Abílio Vilanculos | AG21: 852314121 | AH21: Joaquim Arnaldo Muchanga | AI21: 847870520 | AM21: 260001 | BC21: 15 | BE21: =+BB21+BC21 -> 15 | BF21: =+BE21-H21 -> 0 | BG21: Entregue | BH21: =+VLOOKUP(AF21,Sheet4!A:A,1,FALSE) -> #N/A | BL21: 15 | BM21: =+H21+-BL21 -> 0 | BN21: 0303-0001 | BO21: Nhemba
A22: 46114 | B22: Feijão | F22: 1290 | G22: 1290 | H22: 1035 | I22: -255 | Q22: MXIXFEIJAOKG | U22: 2601052 | V22: Abílio Vilanculos | W22: Maputo | X22: MANHIÇA | Y22: Zona 2 | AF22: Abílio Vilanculos | AG22: 852314121 | AH22: Joaquim Arnaldo Muchanga | AI22: 847870520 | AM22: 260001 | BD22: 1290 | BE22: =+BB22+BC22 -> 0 | BF22: =+BE22-H22 -> -1035 | BG22: Sem registo | BH22: =+VLOOKUP(AF22,Sheet4!A:A,1,FALSE) -> #N/A | BL22: 1290 | BM22: =+H22+-BL22 -> -255 | BN22: 0303-0001 | BO22: Nhemba
A23: 46114 | B23: Feijão | F23: 1050 | G23: 1050 | H23: 855 | I23: -195 | Q23: MXIXFEIJAOKG | U23: 2601052 | V23: Abílio Vilanculos | W23: Maputo | X23: MANHIÇA | Y23: Zona 8 | AF23: Abílio Vilanculos | AG23: 852314121 | AH23: Joaquim Arnaldo Muchanga | AI23: 847870520 | AM23: 260001 | BD23: 1050 | BE23: =+BB23+BC23 -> 0 | BF23: =+BE23-H23 -> -855 | BG23: Sem registo | BH23: =+VLOOKUP(AF23,Sheet4!A:A,1,FALSE) -> #N/A | BL23: 1050 | BM23: =+H23+-BL23 -> -195 | BN23: 0303-0001 | BO23: Nhemba
A24: 46114 | B24: Emamectin | F24: 21 | G24: 10.5 | H24: 17 | I24: -4 | Q24: AGRIFEMMA01L | U24: 2601052 | V24: Abílio Vilanculos | W24: Maputo | X24: MANHIÇA | Y24: Associação agrícola de Malhalhana | AF24: Abílio Vilanculos | AG24: 852314121 | AH24: Joaquim Arnaldo Muchanga | AI24: 847870520 | AM24: 260001 | BE24: =+BB24+BC24 -> 0 | BF24: =+BE24-H24 -> -17 | BG24: Sem registo | BH24: =+VLOOKUP(AF24,Sheet4!A:A,1,FALSE) -> #N/A | BL24: 10.5 | BM24: =+H24+-BL24 -> 6.5 | BN24: 0303-0001
A25: 46114 | B25: Emamectin | F25: 25 | G25: 12.5 | H25: 20 | I25: -5 | Q25: AGRIFEMMA01L | U25: 2601052 | V25: Abílio Vilanculos | W25: Maputo | X25: MANHIÇA | Y25: Associação de Balucuene | AF25: Abílio Vilanculos | AG25: 852314121 | AH25: Joaquim Arnaldo Muchanga | AI25: 847870520 | AM25: 260001 | BE25: =+BB25+BC25 -> 0 | BF25: =+BE25-H25 -> -20 | BG25: Sem registo | BH25: =+VLOOKUP(AF25,Sheet4!A:A,1,FALSE) -> #N/A | BL25: 12.5 | BM25: =+H25+-BL25 -> 7.5 | BN25: 0303-0001
A26: 46114 | B26: Emamectin | F26: 9 | G26: 4.5 | H26: 7 | I26: -2 | Q26: AGRIFEMMA01L | U26: 2601052 | V26: Abílio Vilanculos | W26: Maputo | X26: MANHIÇA | Y26: Associação de Chibucutso | AF26: Abílio Vilanculos | AG26: 852314121 | AH26: Joaquim Arnaldo Muchanga | AI26: 847870520 | AM26: 260001 | BE26: =+BB26+BC26 -> 0 | BF26: =+BE26-H26 -> -7 | BG26: Sem registo | BH26: =+VLOOKUP(AF26,Sheet4!A:A,1,FALSE) -> #N/A | BL26: 4.5 | BM26: =+H26+-BL26 -> 2.5 | BN26: 0303-0001
A27: 46114 | B27: Emamectin | F27: 58 | G27: 29 | H27: 47 | I27: -11 | Q27: AGRIFEMMA01L | U27: 2601052 | V27: Abílio Vilanculos | W27: Maputo | X27: MANHIÇA | Y27: Associação DE Chirindzene | AF27: Abílio Vilanculos | AG27: 852314121 | AH27: Joaquim Arnaldo Muchanga | AI27: 847870520 | AM27: 260001 | BE27: =+BB27+BC27 -> 0 | BF27: =+BE27-H27 -> -47 | BG27: Sem registo | BH27: =+VLOOKUP(AF27,Sheet4!A:A,1,FALSE) -> #N/A | BL27: 29 | BM27: =+H27+-BL27 -> 18 | BN27: 0303-0001
A28: 46114 | B28: Emamectin | F28: 503 | G28: 251.5 | H28: 405 | I28: -98 | Q28: AGRIFEMMA01L | U28: 2601052 | V28: Abílio Vilanculos | W28: Maputo | X28: MANHIÇA | Y28: Chirindzene | AF28: Abílio Vilanculos | AG28: 852314121 | AH28: Joaquim Arnaldo Muchanga | AI28: 847870520 | AM28: 260001 | BE28: =+BB28+BC28 -> 0 | BF28: =+BE28-H28 -> -405 | BG28: Sem registo | BH28: =+VLOOKUP(AF28,Sheet4!A:A,1,FALSE) -> #N/A | BL28: 251.5 | BM28: =+H28+-BL28 -> 153.5 | BN28: 0303-0001
A29: 46114 | B29: Emamectin | F29: 1 | G29: 0.5 | H29: 1 | I29: 0 | Q29: AGRIFEMMA01L | U29: 2601052 | V29: Abílio Vilanculos | W29: Maputo | X29: MANHIÇA | Y29: Manhica-sede | AF29: Abílio Vilanculos | AG29: 852314121 | AH29: Joaquim Arnaldo Muchanga | AI29: 847870520 | AM29: 260001 | BE29: =+BB29+BC29 -> 0 | BF29: =+BE29-H29 -> -1 | BG29: Sem registo | BH29: =+VLOOKUP(AF29,Sheet4!A:A,1,FALSE) -> #N/A | BL29: 0.5 | BM29: =+H29+-BL29 -> 0.5 | BN29: 0303-0001
A30: 46114 | B30: Emamectin | F30: 86 | G30: 43 | H30: 69 | I30: -17 | Q30: AGRIFEMMA01L | U30: 2601052 | V30: Abílio Vilanculos | W30: Maputo | X30: MANHIÇA | Y30: Zona 2 | AF30: Abílio Vilanculos | AG30: 852314121 | AH30: Joaquim Arnaldo Muchanga | AI30: 847870520 | AM30: 260001 | BE30: =+BB30+BC30 -> 0 | BF30: =+BE30-H30 -> -69 | BG30: Sem registo | BH30: =+VLOOKUP(AF30,Sheet4!A:A,1,FALSE) -> #N/A | BL30: 43 | BM30: =+H30+-BL30 -> 26 | BN30: 0303-0001
A31: 46114 | B31: Emamectin | F31: 70 | G31: 35 | H31: 57 | I31: -13 | Q31: AGRIFEMMA01L | U31: 2601052 | V31: Abílio Vilanculos | W31: Maputo | X31: MANHIÇA | Y31: Zona 8 | AF31: Abílio Vilanculos | AG31: 852314121 | AH31: Joaquim Arnaldo Muchanga | AI31: 847870520 | AM31: 260001 | BE31: =+BB31+BC31 -> 0 | BF31: =+BE31-H31 -> -57 | BG31: Sem registo | BH31: =+VLOOKUP(AF31,Sheet4!A:A,1,FALSE) -> #N/A | BL31: 35 | BM31: =+H31+-BL31 -> 22 | BN31: 0303-0001
A32: 46114 | B32: Sacos Hermeticos | F32: 420 | G32: 420 | H32: 340 | I32: -80 | Q32: SUSSACO | U32: 2601052 | V32: Abílio Vilanculos | W32: Maputo | X32: MANHIÇA | Y32: Associação agrícola de Malhalhana | AF32: Abílio Vilanculos | AG32: 852314121 | AH32: Joaquim Arnaldo Muchanga | AI32: 847870520 | AM32: 260001 | BE32: =+BB32+BC32 -> 0 | BF32: =+BE32-H32 -> -340 | BG32: Sem registo | BH32: =+VLOOKUP(AF32,Sheet4!A:A,1,FALSE) -> #N/A | BL32: 420 | BM32: =+H32+-BL32 -> -80 | BN32: 0303-0001
A33: 46114 | B33: Sacos Hermeticos | F33: 500 | G33: 500 | H33: 400 | I33: -100 | Q33: SUSSACO | U33: 2601052 | V33: Abílio Vilanculos | W33: Maputo | X33: MANHIÇA | Y33: Associação de Balucuene | AF33: Abílio Vilanculos | AG33: 852314121 | AH33: Joaquim Arnaldo Muchanga | AI33: 847870520 | AM33: 260001 | BE33: =+BB33+BC33 -> 0 | BF33: =+BE33-H33 -> -400 | BG33: Sem registo | BH33: =+VLOOKUP(AF33,Sheet4!A:A,1,FALSE) -> #N/A | BL33: 500 | BM33: =+H33+-BL33 -> -100 | BN33: 0303-0001
A34: 46114 | B34: Sacos Hermeticos | F34: 180 | G34: 180 | H34: 140 | I34: -40 | Q34: SUSSACO | U34: 2601052 | V34: Abílio Vilanculos | W34: Maputo | X34: MANHIÇA | Y34: Associação de Chibucutso | AF34: Abílio Vilanculos | AG34: 852314121 | AH34: Joaquim Arnaldo Muchanga | AI34: 847870520 | AM34: 260001 | BE34: =+BB34+BC34 -> 0 | BF34: =+BE34-H34 -> -140 | BG34: Sem registo | BH34: =+VLOOKUP(AF34,Sheet4!A:A,1,FALSE) -> #N/A | BL34: 180 | BM34: =+H34+-BL34 -> -40 | BN34: 0303-0001
A35: 46114 | B35: Sacos Hermeticos | F35: 1160 | G35: 1160 | H35: 940 | I35: -220 | Q35: SUSSACO | U35: 2601052 | V35: Abílio Vilanculos | W35: Maputo | X35: MANHIÇA | Y35: Associação DE Chirindzene | AF35: Abílio Vilanculos | AG35: 852314121 | AH35: Joaquim Arnaldo Muchanga | AI35: 847870520 | AM35: 260001 | BE35: =+BB35+BC35 -> 0 | BF35: =+BE35-H35 -> -940 | BG35: Sem registo | BH35: =+VLOOKUP(AF35,Sheet4!A:A,1,FALSE) -> #N/A | BL35: 1160 | BM35: =+H35+-BL35 -> -220 | BN35: 0303-0001
... A47: 46114 | B47: Imadocloprid | F47: 70 | G47: 35 | H47: 57 | I47: -13 | Q47: AGRIMIDACLORP1L | U47: 2601052 | V47: Abílio Vilanculos | W47: Maputo | X47: MANHIÇA | Y47: Zona 8 | AF47: Abílio Vilanculos | AG47: 852314121 | AH47: Joaquim Arnaldo Muchanga | AI47: 847870520 | AM47: 260001 | BE47: =+BB47+BC47 -> 0 | BF47: =+BE47-H47 -> -57 | BG47: Sem registo | BH47: =+VLOOKUP(AF47,Sheet4!A:A,1,FALSE) -> #N/A | BL47: 35 | BM47: =+H47+-BL47 -> 22 | BN47: 0303-0001
A48: 46114 | B48: Milho | F48: 262.5 | G48: 262.5 | H48: 212.5 | I48: -50 | Q48: MXIXMILHOKG | U48: 2601052 | V48: Abílio Vilanculos | W48: Maputo | X48: MANHIÇA | Y48: Associação agrícola de Malhalhana | AF48: Abílio Vilanculos | AG48: 852314121 | AH48: Joaquim Arnaldo Muchanga | AI48: 847870520 | AM48: 260001 | BB48: 262 | BE48: =+BB48+BC48 -> 262 | BF48: =+BE48-H48 -> 49.5 | BG48: Entregue | BH48: =+VLOOKUP(AF48,Sheet4!A:A,1,FALSE) -> #N/A | BL48: 262.5 | BM48: =+H48+-BL48 -> -50 | BN48: 0303-0001
A49: 46114 | B49: Milho | F49: 312.5 | G49: 312.5 | H49: 250 | I49: -62.5 | Q49: MXIXMILHOKG | U49: 2601052 | V49: Abílio Vilanculos | W49: Maputo | X49: MANHIÇA | Y49: Associação de Balucuene | AF49: Abílio Vilanculos | AG49: 852314121 | AH49: Joaquim Arnaldo Muchanga | AI49: 847870520 | AM49: 260001 | BB49: 312 | BE49: =+BB49+BC49 -> 312 | BF49: =+BE49-H49 -> 62 | BG49: Entregue | BH49: =+VLOOKUP(AF49,Sheet4!A:A,1,FALSE) -> #N/A | BL49: 312.5 | BM49: =+H49+-BL49 -> -62.5 | BN49: 0303-0001
A50: 46114 | B50: Milho | F50: 112.5 | G50: 112.5 | H50: 87.5 | I50: -25 | Q50: MXIXMILHOKG | U50: 2601052 | V50: Abílio Vilanculos | W50: Maputo | X50: MANHIÇA | Y50: Associação de Chibucutso | AF50: Abílio Vilanculos | AG50: 852314121 | AH50: Joaquim Arnaldo Muchanga | AI50: 847870520 | AM50: 260001 | BB50: 112 | BE50: =+BB50+BC50 -> 112 | BF50: =+BE50-H50 -> 24.5 | BG50: Entregue | BH50: =+VLOOKUP(AF50,Sheet4!A:A,1,FALSE) -> #N/A | BL50: 112.5 | BM50: =+H50+-BL50 -> -25 | BN50: 0303-0001
A51: 46114 | B51: Milho | F51: 725 | G51: 725 | H51: 587.5 | I51: -137.5 | Q51: MXIXMILHOKG | U51: 2601052 | V51: Abílio Vilanculos | W51: Maputo | X51: MANHIÇA | Y51: Associação DE Chirindzene | AF51: Abílio Vilanculos | AG51: 852314121 | AH51: Joaquim Arnaldo Muchanga | AI51: 847870520 | AM51: 260001 | BB51: 725 | BE51: =+BB51+BC51 -> 725 | BF51: =+BE51-H51 -> 137.5 | BG51: Entregue | BH51: =+VLOOKUP(AF51,Sheet4!A:A,1,FALSE) -> #N/A | BL51: 725 | BM51: =+H51+-BL51 -> -137.5 | BN51: 0303-0001
A52: 46114 | B52: Milho | F52: 6287.5 | G52: 6287.5 | H52: 5062.5 | I52: -1225 | Q52: MXIXMILHOKG | U52: 2601052 | V52: Abílio Vilanculos | W52: Maputo | X52: MANHIÇA | Y52: Chirindzene | AF52: Abílio Vilanculos | AG52: 852314121 | AH52: Joaquim Arnaldo Muchanga | AI52: 847870520 | AM52: 260001 | BB52: 6288 | BE52: =+BB52+BC52 -> 6288 | BF52: =+BE52-H52 -> 1225.5 | BG52: Entregue | BH52: =+VLOOKUP(AF52,Sheet4!A:A,1,FALSE) -> #N/A | BL52: 6287.5 | BM52: =+H52+-BL52 -> -1225 | BN52: 0303-0001
A53: 46114 | B53: Milho | F53: 12.5 | G53: 12.5 | H53: 12.5 | I53: 0 | Q53: MXIXMILHOKG | U53: 2601052 | V53: Abílio Vilanculos | W53: Maputo | X53: MANHIÇA | Y53: Manhica-sede | AF53: Abílio Vilanculos | AG53: 852314121 | AH53: Joaquim Arnaldo Muchanga | AI53: 847870520 | AM53: 260001 | BB53: 12 | BE53: =+BB53+BC53 -> 12 | BF53: =+BE53-H53 -> -0.5 | BG53: Entregue | BH53: =+VLOOKUP(AF53,Sheet4!A:A,1,FALSE) -> #N/A | BL53: 12.5 | BM53: =+H53+-BL53 -> 0 | BN53: 0303-0001
A54: 46114 | B54: Milho | F54: 1075 | G54: 1075 | H54: 862.5 | I54: -212.5 | Q54: MXIXMILHOKG | U54: 2601052 | V54: Abílio Vilanculos | W54: Maputo | X54: MANHIÇA | Y54: Zona 2 | AF54: Abílio Vilanculos | AG54: 852314121 | AH54: Joaquim Arnaldo Muchanga | AI54: 847870520 | AM54: 260001 | BB54: 1075 | BE54: =+BB54+BC54 -> 1075 | BF54: =+BE54-H54 -> 212.5 | BG54: Entregue | BH54: =+VLOOKUP(AF54,Sheet4!A:A,1,FALSE) -> #N/A | BL54: 1075 | BM54: =+H54+-BL54 -> -212.5 | BN54: 0303-0001
A55: 46114 | B55: Milho | F55: 875 | G55: 875 | H55: 712.5 | I55: -162.5 | Q55: MXIXMILHOKG | U55: 2601052 | V55: Abílio Vilanculos | W55: Maputo | X55: MANHIÇA | Y55: Zona 8 | AF55: Abílio Vilanculos | AG55: 852314121 | AH55: Joaquim Arnaldo Muchanga | AI55: 847870520 | AM55: 260001 | BB55: 875 | BE55: =+BB55+BC55 -> 875 | BF55: =+BE55-H55 -> 162.5 | BG55: Entregue | BH55: =+VLOOKUP(AF55,Sheet4!A:A,1,FALSE) -> #N/A | BL55: 875 | BM55: =+H55+-BL55 -> -162.5 | BN55: 0303-0001
A56: 46114 | B56: Feijão | F56: 11445 | G56: 11445 | H56: 9997.588 | I56: =H56-G56 -> -1447.412 | Q56: MXIXFEIJAOKG | U56: 2601053 | V56: Acacio Emilio Policarpo | W56: Sofala | X56: Machanga | Y56: Javane | AF56: Acacio Emilio Policarpo | AG56: 867197531 | AH56: Samuel R. M. Matate | AI56: 844823720 | AM56: 260001 | BA56: -1447.412 | BD56: 11445 | BE56: =+BB56+BC56 -> 0 | BF56: =+BE56-H56 -> -9997.588 | BG56: Sem registo | BH56: =+VLOOKUP(AF56,Sheet4!A:A,1,FALSE) -> #N/A | BL56: 10005 | BM56: =+H56+-BL56 -> -7.4119948 | BN56: 0408-0001 | BO56: Nhemba e Vulgar
A57: 46114 | B57: Feijão | F57: 60 | G57: 60 | H57: 52.411995 | I57: =H57-G57 -> -7.5880052 | Q57: MXIXFEIJAOKG | U57: 2601053 | V57: Acacio Emilio Policarpo | W57: Sofala | X57: Machanga | Y57: Zimuala | AF57: Acacio Emilio Policarpo | AG57: 867197531 | AH57: Samuel R. M. Matate | AI57: 844823720 | AM57: 260001 | BA57: -7.5880052 | BD57: 60 | BE57: =+BB57+BC57 -> 0 | BF57: =+BE57-H57 -> -52.411995 | BG57: Sem registo | BH57: =+VLOOKUP(AF57,Sheet4!A:A,1,FALSE) -> #N/A | BL57: 45 | BM57: =+H57+-BL57 -> 7.4119948 | BN57: 0408-0001 | BO57: Nhemba e Vulgar
A58: 46114 | B58: Emamectin | F58: 763 | G58: 381.5 | H58: 666.50587 | I58: =H58-G58 -> 285.00587 | Q58: AGRIFEMMA01L | U58: 2601053 | V58: Acacio Emilio Policarpo | W58: Sofala | X58: Machanga | Y58: Javane | AF58: Acacio Emilio Policarpo | AG58: 867197531 | AH58: Samuel R. M. Matate | AI58: 844823720 | AM58: 260001 | BA58: -96.494133 | BE58: =+BB58+BC58 -> 0 | BF58: =+BE58-H58 -> -666.50587 | BG58: Sem registo | BH58: =+VLOOKUP(AF58,Sheet4!A:A,1,FALSE) -> #N/A | BL58: 667 | BM58: =+H58+-BL58 -> -0.49413299 | BN58: 0408-0001
A59: 46114 | B59: Emamectin | F59: 4 | G59: 2 | H59: 3.494133 | I59: =H59-G59 -> 1.494133 | Q59: AGRIFEMMA01L | U59: 2601053 | V59: Acacio Emilio Policarpo | W59: Sofala | X59: Machanga | Y59: Zimuala | AF59: Acacio Emilio Policarpo | AG59: 867197531 | AH59: Samuel R. M. Matate | AI59: 844823720 | AM59: 260001 | BA59: -0.50586701 | BE59: =+BB59+BC59 -> 0 | BF59: =+BE59-H59 -> -3.494133 | BG59: Sem registo | BH59: =+VLOOKUP(AF59,Sheet4!A:A,1,FALSE) -> #N/A | BL59: 3 | BM59: =+H59+-BL59 -> 0.49413299 | BN59: 0408-0001
A60: 46114 | B60: Sacos Hermeticos | F60: 15260 | G60: 15260 | H60: 13330.117 | I60: =H60-G60 -> -1929.8827 | Q60: SUSSACO | U60: 2601053 | V60: Acacio Emilio Policarpo | W60: Sofala | X60: Machanga | Y60: Javane | AF60: Acacio Emilio Policarpo | AG60: 867197531 | AH60: Samuel R. M. Matate | AI60: 844823720 | AM60: 260001 | BA60: -1929.8827 | BE60: =+BB60+BC60 -> 0 | BF60: =+BE60-H60 -> -13330.117 | BG60: Sem registo | BH60: =+VLOOKUP(AF60,Sheet4!A:A,1,FALSE) -> #N/A | BL60: 13340 | BM60: =+H60+-BL60 -> -9.8826597 | BN60: 0408-0001
A61: 46114 | B61: Sacos Hermeticos | F61: 80 | G61: 80 | H61: 69.88266 | I61: =H61-G61 -> -10.11734 | Q61: SUSSACO | U61: 2601053 | V61: Acacio Emilio Policarpo | W61: Sofala | X61: Machanga | Y61: Zimuala | AF61: Acacio Emilio Policarpo | AG61: 867197531 | AH61: Samuel R. M. Matate | AI61: 844823720 | AM61: 260001 | BA61: -10.11734 | BE61: =+BB61+BC61 -> 0 | BF61: =+BE61-H61 -> -69.88266 | BG61: Sem registo | BH61: =+VLOOKUP(AF61,Sheet4!A:A,1,FALSE) -> #N/A | BL61: 60 | BM61: =+H61+-BL61 -> 9.8826597 | BN61: 0408-0001
A62: 46114 | B62: Imadocloprid | F62: 763 | G62: 381.5 | H62: 666.50587 | I62: =H62-G62 -> 285.00587 | Q62: AGRIMIDACLORP1L | U62: 2601053 | V62: Acacio Emilio Policarpo | W62: Sofala | X62: Machanga | Y62: Javane | AF62: Acacio Emilio Policarpo | AG62: 867197531 | AH62: Samuel R. M. Matate | AI62: 844823720 | AM62: 260001 | BA62: -96.494133 | BE62: =+BB62+BC62 -> 0 | BF62: =+BE62-H62 -> -666.50587 | BG62: Sem registo | BH62: =+VLOOKUP(AF62,Sheet4!A:A,1,FALSE) -> #N/A | BL62: 667 | BM62: =+H62+-BL62 -> -0.49413299 | BN62: 0408-0001
A63: 46114 | B63: Imadocloprid | F63: 4 | G63: 2 | H63: 3.494133 | I63: =H63-G63 -> 1.494133 | Q63: AGRIMIDACLORP1L | U63: 2601053 | V63: Acacio Emilio Policarpo | W63: Sofala | X63: Machanga | Y63: Zimuala | AF63: Acacio Emilio Policarpo | AG63: 867197531 | AH63: Samuel R. M. Matate | AI63: 844823720 | AM63: 260001 | BA63: -0.50586701 | BE63: =+BB63+BC63 -> 0 | BF63: =+BE63-H63 -> -3.494133 | BG63: Sem registo | BH63: =+VLOOKUP(AF63,Sheet4!A:A,1,FALSE) -> #N/A | BL63: 3 | BM63: =+H63+-BL63 -> 0.49413299 | BN63: 0408-0001
A64: 46114 | B64: Milho | F64: 9537.5 | G64: 9537.5 | H64: 8331.3233 | I64: =H64-G64 -> -1206.1767 | Q64: MXIXMILHOKG | U64: 2601053 | V64: Acacio Emilio Policarpo | W64: Sofala | X64: Machanga | Y64: Javane | AF64: Acacio Emilio Policarpo | AG64: 867197531 | AH64: Samuel R. M. Matate | AI64: 844823720 | AM64: 260001 | BA64: -1206.1767 | BC64: 9538 | BE64: =+BB64+BC64 -> 9538 | BF64: =+BE64-H64 -> 1206.6767 | BG64: Entregue | BH64: =+VLOOKUP(AF64,Sheet4!A:A,1,FALSE) -> #N/A | BL64: 8337.5 | BM64: =+H64+-BL64 -> -6.1766623 | BN64: 0408-0001
A65: 46114 | B65: Milho | F65: 50 | G65: 50 | H65: 43.676662 | I65: =H65-G65 -> -6.3233377 | Q65: MXIXMILHOKG | U65: 2601053 | V65: Acacio Emilio Policarpo | W65: Sofala | X65: Machanga | Y65: Zimuala | AF65: Acacio Emilio Policarpo | AG65: 867197531 | AH65: Samuel R. M. Matate | AI65: 844823720 | AM65: 260001 | BA65: -6.3233377 | BC65: 50 | BE65: =+BB65+BC65 -> 50 | BF65: =+BE65-H65 -> 6.3233377 | BG65: Entregue | BH65: =+VLOOKUP(AF65,Sheet4!A:A,1,FALSE) -> #N/A | BL65: 37.5 | BM65: =+H65+-BL65 -> 6.1766623 | BN65: 0408-0001
A66: 46114 | B66: Feijão | F66: 300 | G66: 300 | H66: 0 | I66: =H66-G66 -> -300 | Q66: MXIXFEIJAOKG | U66: 2601054 | V66: Acson Ali Elobolobo | W66: Tete | X66: Cahora Bassa | Y66: Chintholo | AF66: Acson Ali Elobolobo | AG66: 845755258 | AH66: Manuel Noe Budo | AI66: 861003151 | AM66: 260001 | BA66: -300 | BE66: =+BB66+BC66 -> 0 | BF66: =+BE66-H66 -> 0 | BG66: Sem registo | BH66: =+VLOOKUP(AF66,Sheet4!A:A,1,FALSE) -> #N/A | BL66: 0 | BM66: =+H66+-BL66 -> 0 | BN66: 0502-0001 | BO66: Nhemba
A67: 46114 | B67: Emamectin | F67: 20 | G67: 10 | H67: 0 | I67: =H67-G67 -> -10 | Q67: AGRIFEMMA01L | U67: 2601054 | V67: Acson Ali Elobolobo | W67: Tete | X67: Cahora Bassa | Y67: Chintholo | AF67: Acson Ali Elobolobo | AG67: 845755258 | AH67: Manuel Noe Budo | AI67: 861003151 | AM67: 260001 | BA67: -20 | BE67: =+BB67+BC67 -> 0 | BF67: =+BE67-H67 -> 0 | BG67: Sem registo | BH67: =+VLOOKUP(AF67,Sheet4!A:A,1,FALSE) -> #N/A | BL67: 0 | BM67: =+H67+-BL67 -> 0 | BN67: 0502-0001
A68: 46114 | B68: Sacos Hermeticos | F68: 400 | G68: 400 | H68: 0 | I68: =H68-G68 -> -400 | Q68: SUSSACO | U68: 2601054 | V68: Acson Ali Elobolobo | W68: Tete | X68: Cahora Bassa | Y68: Chintholo | AF68: Acson Ali Elobolobo | AG68: 845755258 | AH68: Manuel Noe Budo | AI68: 861003151 | AM68: 260001 | BA68: -400 | BE68: =+BB68+BC68 -> 0 | BF68: =+BE68-H68 -> 0 | BG68: Sem registo | BH68: =+VLOOKUP(AF68,Sheet4!A:A,1,FALSE) -> #N/A | BL68: 0 | BM68: =+H68+-BL68 -> 0 | BN68: 0502-0001
A69: 46114 | B69: Imadocloprid | F69: 20 | G69: 10 | H69: 0 | I69: =H69-G69 -> -10 | Q69: AGRIMIDACLORP1L | U69: 2601054 | V69: Acson Ali Elobolobo | W69: Tete | X69: Cahora Bassa | Y69: Chintholo | AF69: Acson Ali Elobolobo | AG69: 845755258 | AH69: Manuel Noe Budo | AI69: 861003151 | AM69: 260001 | BA69: -20 | BE69: =+BB69+BC69 -> 0 | BF69: =+BE69-H69 -> 0 | BG69: Sem registo | BH69: =+VLOOKUP(AF69,Sheet4!A:A,1,FALSE) -> #N/A | BL69: 0 | BM69: =+H69+-BL69 -> 0 | BN69: 0502-0001
A70: 46114 | B70: Milho | F70: 250 | G70: 250 | H70: 0 | I70: =H70-G70 -> -250 | Q70: MXIXMILHOKG | U70: 2601054 | V70: Acson Ali Elobolobo | W70: Tete | X70: Cahora Bassa | Y70: Chintholo | AF70: Acson Ali Elobolobo | AG70: 845755258 | AH70: Manuel Noe Budo | AI70: 861003151 | AM70: 260001 | BA70: -250 | BE70: =+BB70+BC70 -> 0 | BF70: =+BE70-H70 -> 0 | BG70: Sem registo | BH70: =+VLOOKUP(AF70,Sheet4!A:A,1,FALSE) -> #N/A | BL70: 0 | BM70: =+H70+-BL70 -> 0 | BN70: 0502-0001
A71: 46114 | B71: Feijão | F71: 29955 | G71: 29955 | H71: 8055 | I71: =H71-G71 -> -21900 | Q71: MXIXFEIJAOKG | U71: 2601055 | V71: Adelina Massora | W71: Sofala | X71: Buzi | Y71: Inharongue | AF71: Adelina Massora | AG71: 867878815 | AH71: Ayrton Mael | AI71: 879095867 | AM71: 260001 | BA71: -21900 | BD71: 29955 | BE71: =+BB71+BC71 -> 0 | BF71: =+BE71-H71 -> -8055 | BG71: Sem registo | BH71: =+VLOOKUP(AF71,Sheet4!A:A,1,FALSE) -> #N/A | BL71: 8055 | BM71: =+H71+-BL71 -> 0 | BN71: 0402-0001 | BO71: Vulgar
A72: 46114 | B72: Emamectin | F72: 1997 | G72: 998.5 | H72: 537 | I72: =H72-G72 -> -461.5 | Q72: AGRIFEMMA01L | U72: 2601055 | V72: Adelina Massora | W72: Sofala | X72: Buzi | Y72: Inharongue | AF72: Adelina Massora | AG72: 867878815 | AH72: Ayrton Mael | AI72: 879095867 | AM72: 260001 | BA72: -1460 | BE72: =+BB72+BC72 -> 0 | BF72: =+BE72-H72 -> -537 | BG72: Sem registo | BH72: =+VLOOKUP(AF72,Sheet4!A:A,1,FALSE) -> #N/A | BL72: 537 | BM72: =+H72+-BL72 -> 0 | BN72: 0402-0001
A73: 46114 | B73: Sacos Hermeticos | F73: 39940 | G73: 39940 | H73: 10740 | I73: =H73-G73 -> -29200 | Q73: SUSSACO | U73: 2601055 | V73: Adelina Massora | W73: Sofala | X73: Buzi | Y73: Inharongue | AF73: Adelina Massora | AG73: 867878815 | AH73: Ayrton Mael | AI73: 879095867 | AM73: 260001 | BA73: -29200 | BE73: =+BB73+BC73 -> 0 | BF73: =+BE73-H73 -> -10740 | BG73: Sem registo | BH73: =+VLOOKUP(AF73,Sheet4!A:A,1,FALSE) -> #N/A | BL73: 10740 | BM73: =+H73+-BL73 -> 0 | BN73: 0402-0001
A74: 46114 | B74: MCPA | F74: 5991 | G74: 2995.5 | H74: 264 | I74: =H74-G74 -> -2731.5 | Q74: AGRIMHMCPA1L | U74: 2601055 | V74: Adelina Massora | W74: Sofala | X74: Buzi | Y74: Inharongue | AF74: Adelina Massora | AG74: 867878815 | AH74: Ayrton Mael | AI74: 879095867 | AM74: 260001 | BA74: -5727 | BE74: =+BB74+BC74 -> 0 | BF74: =+BE74-H74 -> -264 | BG74: Sem registo | BH74: =+VLOOKUP(AF74,Sheet4!A:A,1,FALSE) -> #N/A | BL74: 264 | BM74: =+H74+-BL74 -> 0 | BN74: 0402-0001
A75: 46114 | B75: Arroz | F75: 99850 | G75: 99850 | H75: 4400 | I75: =H75-G75 -> -95450 | Q75: MXIXARROZKG | U75: 2601055 | V75: Adelina Massora | W75: Sofala | X75: Buzi | Y75: Inharongue | AF75: Adelina Massora | AG75: 867878815 | AH75: Ayrton Mael | AI75: 879095867 | AM75: 260001 | BA75: -95450 | BE75: =+BB75+BC75 -> 0 | BF75: =+BE75-H75 -> -4400 | BG75: Sem registo | BH75: =+VLOOKUP(AF75,Sheet4!A:A,1,FALSE) -> #N/A | BL75: 4400 | BM75: =+H75+-BL75 -> 0 | BN75: 0402-0001
A76: 46114 | B76: Feijão | F76: 13275 | G76: 13275 | H76: 5925 | I76: =H76-G76 -> -7350 | Q76: MXIXFEIJAOKG | U76: 2601056 | V76: Adelino Patrício Bitone Chuca | W76: Sofala | X76: Nhamatanda | Y76: Metuchira | AF76: Adelino Patrício Bitone Chuca | AG76: 842674056 | AH76: Anastacio Mauro Vasconcelos | AI76: 840522555 | AM76: 260001 | BA76: -7350 | BE76: =+BB76+BC76 -> 0 | BF76: =+BE76-H76 -> -5925 | BG76: Sem registo | BH76: =+VLOOKUP(AF76,Sheet4!A:A,1,FALSE) -> #N/A | BL76: 5925 | BM76: =+H76+-BL76 -> 0 | BN76: 0411-0001 | BO76: Nhemba
A77: 46114 | B77: Emamectin | F77: 885 | G77: 442.5 | H77: 395 | I77: =H77-G77 -> -47.5 | Q77: AGRIFEMMA01L | U77: 2601056 | V77: Adelino Patrício Bitone Chuca | W77: Sofala | X77: Nhamatanda | Y77: Metuchira | AF77: Adelino Patrício Bitone Chuca | AG77: 842674056 | AH77: Anastacio Mauro Vasconcelos | AI77: 840522555 | AM77: 260001 | BA77: -490 | BE77: =+BB77+BC77 -> 0 | BF77: =+BE77-H77 -> -395 | BG77: Sem registo | BH77: =+VLOOKUP(AF77,Sheet4!A:A,1,FALSE) -> #N/A | BL77: 395 | BM77: =+H77+-BL77 -> 0 | BN77: 0411-0001
A78: 46114 | B78: Sacos Hermeticos | F78: 17700 | G78: 17700 | H78: 7900 | I78: =H78-G78 -> -9800 | Q78: SUSSACO | U78: 2601056 | V78: Adelino Patrício Bitone Chuca | W78: Sofala | X78: Nhamatanda | Y78: Metuchira | AF78: Adelino Patrício Bitone Chuca | AG78: 842674056 | AH78: Anastacio Mauro Vasconcelos | AI78: 840522555 | AM78: 260001 | BA78: -9800 | BE78: =+BB78+BC78 -> 0 | BF78: =+BE78-H78 -> -7900 | BG78: Sem registo | BH78: =+VLOOKUP(AF78,Sheet4!A:A,1,FALSE) -> #N/A | BL78: 7900 | BM78: =+H78+-BL78 -> 0 | BN78: 0411-0001
A79: 46114 | B79: Imadocloprid | F79: 885 | G79: 442.5 | H79: 395 | I79: =H79-G79 -> -47.5 | Q79: AGRIMIDACLORP1L | U79: 2601056 | V79: Adelino Patrício Bitone Chuca | W79: Sofala | X79: Nhamatanda | Y79: Metuchira | AF79: Adelino Patrício Bitone Chuca | AG79: 842674056 | AH79: Anastacio Mauro Vasconcelos | AI79: 840522555 | AM79: 260001 | BA79: -490 | BE79: =+BB79+BC79 -> 0 | BF79: =+BE79-H79 -> -395 | BG79: Sem registo | BH79: =+VLOOKUP(AF79,Sheet4!A:A,1,FALSE) -> #N/A | BL79: 395 | BM79: =+H79+-BL79 -> 0 | BN79: 0411-0001
A80: 46114 | B80: Milho | F80: 11062.5 | G80: 11062.5 | H80: 4937.5 | I80: =H80-G80 -> -6125 | Q80: MXIXMILHOKG | U80: 2601056 | V80: Adelino Patrício Bitone Chuca | W80: Sofala | X80: Nhamatanda | Y80: Metuchira | AF80: Adelino Patrício Bitone Chuca | AG80: 842674056 | AH80: Anastacio Mauro Vasconcelos | AI80: 840522555 | AM80: 260001 | BA80: -6125 | BC80: 11062 | BE80: =+BB80+BC80 -> 11062 | BF80: =+BE80-H80 -> 6124.5 | BG80: Entregue | BH80: =+VLOOKUP(AF80,Sheet4!A:A,1,FALSE) -> #N/A | BL80: 4937.5 | BM80: =+H80+-BL80 -> 0 | BN80: 0411-0001
A81: 46114 | B81: Feijão | F81: 60 | G81: 60 | H81: 60 | I81: =H81-G81 -> 0 | Q81: MXIXFEIJAOKG | U81: 2601057 | V81: Adia Manguengue | W81: Sofala | X81: Beira | Y81: Soger | AF81: Adia Manguengue | AG81: 845248854 | AH81: Anifa Manuel Ferreira Ramessane | AI81: 843766667 | AM81: 260001 | BA81: 0 | BD81: 60 | BE81: =+BB81+BC81 -> 0 | BF81: =+BE81-H81 -> -60 | BG81: Sem registo | BH81: =+VLOOKUP(AF81,Sheet4!A:A,1,FALSE) -> #N/A | BL81: 60 | BM81: =+H81+-BL81 -> 0 | BN81: 0401-0001 | BO81: Vulgar
A82: 46114 | B82: Emamectin | F82: 4 | G82: 2 | H82: 4 | I82: =H82-G82 -> 2 | Q82: AGRIFEMMA01L | U82: 2601057 | V82: Adia Manguengue | W82: Sofala | X82: Beira | Y82: Soger | AF82: Adia Manguengue | AG82: 845248854 | AH82: Anifa Manuel Ferreira Ramessane | AI82: 843766667 | AM82: 260001 | BA82: 0 | BE82: =+BB82+BC82 -> 0 | BF82: =+BE82-H82 -> -4 | BG82: Sem registo | BH82: =+VLOOKUP(AF82,Sheet4!A:A,1,FALSE) -> #N/A | BL82: 4 | BM82: =+H82+-BL82 -> 0 | BN82: 0401-0001
A83: 46114 | B83: Sacos Hermeticos | F83: 80 | G83: 80 | H83: 80 | I83: =H83-G83 -> 0 | Q83: SUSSACO | U83: 2601057 | V83: Adia Manguengue | W83: Sofala | X83: Beira | Y83: Soger | AF83: Adia Manguengue | AG83: 845248854 | AH83: Anifa Manuel Ferreira Ramessane | AI83: 843766667 | AM83: 260001 | BA83: 0 | BE83: =+BB83+BC83 -> 0 | BF83: =+BE83-H83 -> -80 | BG83: Sem registo | BH83: =+VLOOKUP(AF83,Sheet4!A:A,1,FALSE) -> #N/A | BL83: 80 | BM83: =+H83+-BL83 -> 0 | BN83: 0401-0001
A84: 46114 | B84: MCPA | F84: 12 | G84: 6 | H84: 12 | I84: =H84-G84 -> 6 | Q84: AGRIMHMCPA1L | U84: 2601057 | V84: Adia Manguengue | W84: Sofala | X84: Beira | Y84: Soger | AF84: Adia Manguengue | AG84: 845248854 | AH84: Anifa Manuel Ferreira Ramessane | AI84: 843766667 | AM84: 260001 | BA84: 0 | BE84: =+BB84+BC84 -> 0 | BF84: =+BE84-H84 -> -12 | BG84: Sem registo | BH84: =+VLOOKUP(AF84,Sheet4!A:A,1,FALSE) -> #N/A | BL84: 12 | BM84: =+H84+-BL84 -> 0 | BN84: 0401-0001
A85: 46114 | B85: Arroz | F85: 200 | G85: 200 | H85: 200 | I85: =H85-G85 -> 0 | Q85: MXIXARROZKG | U85: 2601057 | V85: Adia Manguengue | W85: Sofala | X85: Beira | Y85: Soger | AF85: Adia Manguengue | AG85: 845248854 | AH85: Anifa Manuel Ferreira Ramessane | AI85: 843766667 | AM85: 260001 | BA85: 0 | BE85: =+BB85+BC85 -> 0 | BF85: =+BE85-H85 -> -200 | BG85: Sem registo | BH85: =+VLOOKUP(AF85,Sheet4!A:A,1,FALSE) -> #N/A | BL85: 200 | BM85: =+H85+-BL85 -> 0 | BN85: 0401-0001
A86: 46114 | B86: Feijão | F86: 225 | G86: 225 | H86: 0 | I86: =H86-G86 -> -225 | Q86: MXIXFEIJAOKG | U86: 2601058 | V86: Admiro Lourenço Aniva | W86: Manica | X86: Macate | Y86: Trangapasso | AF86: Admiro Lourenço Aniva | AG86: 848160962 / 862692780 | AH86: Constantino João Fernando | AI86: 846867910 / 865989486 | AM86: 260001 | BA86: -225 | BE86: =+BB86+BC86 -> 0 | BF86: =+BE86-H86 -> 0 | BG86: Sem registo | BH86: =+VLOOKUP(AF86,Sheet4!A:A,1,FALSE) -> #N/A | BL86: 0 | BM86: =+H86+-BL86 -> 0 | BN86: 0204-0001 | BO86: Nhemba
A87: 46114 | B87: Emamectin | F87: 15 | G87: 7.5 | H87: 0 | I87: =H87-G87 -> -7.5 | Q87: AGRIFEMMA01L | U87: 2601058 | V87: Admiro Lourenço Aniva | W87: Manica | X87: Macate | Y87: Trangapasso | AF87: Admiro Lourenço Aniva | AG87: 848160962 / 862692780 | AH87: Constantino João Fernando | AI87: 846867910 / 865989486 | AM87: 260001 | BA87: -15 | BE87: =+BB87+BC87 -> 0 | BF87: =+BE87-H87 -> 0 | BG87: Sem registo | BH87: =+VLOOKUP(AF87,Sheet4!A:A,1,FALSE) -> #N/A | BL87: 0 | BM87: =+H87+-BL87 -> 0 | BN87: 0204-0001
A88: 46114 | B88: Sacos Hermeticos | F88: 300 | G88: 300 | H88: 0 | I88: =H88-G88 -> -300 | Q88: SUSSACO | U88: 2601058 | V88: Admiro Lourenço Aniva | W88: Manica | X88: Macate | Y88: Trangapasso | AF88: Admiro Lourenço Aniva | AG88: 848160962 / 862692780 | AH88: Constantino João Fernando | AI88: 846867910 / 865989486 | AM88: 260001 | BA88: -300 | BE88: =+BB88+BC88 -> 0 | BF88: =+BE88-H88 -> 0 | BG88: Sem registo | BH88: =+VLOOKUP(AF88,Sheet4!A:A,1,FALSE) -> #N/A | BL88: 0 | BM88: =+H88+-BL88 -> 0 | BN88: 0204-0001
A89: 46114 | B89: Imadocloprid | F89: 15 | G89: 7.5 | H89: 0 | I89: =H89-G89 -> -7.5 | Q89: AGRIMIDACLORP1L | U89: 2601058 | V89: Admiro Lourenço Aniva | W89: Manica | X89: Macate | Y89: Trangapasso | AF89: Admiro Lourenço Aniva | AG89: 848160962 / 862692780 | AH89: Constantino João Fernando | AI89: 846867910 / 865989486 | AM89: 260001 | BA89: -15 | BE89: =+BB89+BC89 -> 0 | BF89: =+BE89-H89 -> 0 | BG89: Sem registo | BH89: =+VLOOKUP(AF89,Sheet4!A:A,1,FALSE) -> #N/A | BL89: 0 | BM89: =+H89+-BL89 -> 0 | BN89: 0204-0001
A90: 46114 | B90: Milho | F90: 187.5 | G90: 187.5 | H90: 0 | I90: =H90-G90 -> -187.5 | Q90: MXIXMILHOKG | U90: 2601058 | V90: Admiro Lourenço Aniva | W90: Manica | X90: Macate | Y90: Trangapasso | AF90: Admiro Lourenço Aniva | AG90: 848160962 / 862692780 | AH90: Constantino João Fernando | AI90: 846867910 / 865989486 | AM90: 260001 | BA90: -187.5 | BE90: =+BB90+BC90 -> 0 | BF90: =+BE90-H90 -> 0 | BG90: Sem registo | BH90: =+VLOOKUP(AF90,Sheet4!A:A,1,FALSE) -> #N/A | BL90: 0 | BM90: =+H90+-BL90 -> 0 | BN90: 0204-0001
A91: 46114 | B91: Feijão | F91: 540 | G91: 540 | H91: 630 | I91: =H91-G91 -> 90 | Q91: MXIXFEIJAOKG | U91: 2601059 | V91: Adolfo Almeida | W91: Zambezia | X91: Mulevala | Y91: Chiraco sede | AF91: Adolfo Almeida | AG91: 840560264 | AH91: Forencio Antonio Uatelauene | AI91: 849370189 /861682 | AM91: 260001 | BA91: 90 | BE91: =+BB91+BC91 -> 0 | BF91: =+BE91-H91 -> -630 | BG91: Sem registo | BH91: =+VLOOKUP(AF91,Sheet4!A:A,1,FALSE) -> #N/A | BL91: 630 | BM91: =+H91+-BL91 -> 0 | BN91: 0614-0001 | BO91: Nhemba
A92: 46114 | B92: Emamectin | F92: 36 | G92: 18 | H92: 42 | I92: =H92-G92 -> 24 | Q92: AGRIFEMMA01L | U92: 2601059 | V92: Adolfo Almeida | W92: Zambezia | X92: Mulevala | Y92: Chiraco sede | AF92: Adolfo Almeida | AG92: 840560264 | AH92: Forencio Antonio Uatelauene | AI92: 849370189 /861682 | AM92: 260001 | BA92: 6 | BE92: =+BB92+BC92 -> 0 | BF92: =+BE92-H92 -> -42 | BG92: Sem registo | BH92: =+VLOOKUP(AF92,Sheet4!A:A,1,FALSE) -> #N/A | BL92: 42 | BM92: =+H92+-BL92 -> 0 | BN92: 0614-0001
A93: 46114 | B93: Sacos Hermeticos | F93: 720 | G93: 720 | H93: 840 | I93: =H93-G93 -> 120 | Q93: SUSSACO | U93: 2601059 | V93: Adolfo Almeida | W93: Zambezia | X93: Mulevala | Y93: Chiraco sede | AF93: Adolfo Almeida | AG93: 840560264 | AH93: Forencio Antonio Uatelauene | AI93: 849370189 /861682 | AM93: 260001 | BA93: 120 | BE93: =+BB93+BC93 -> 0 | BF93: =+BE93-H93 -> -840 | BG93: Sem registo | BH93: =+VLOOKUP(AF93,Sheet4!A:A,1,FALSE) -> #N/A | BL93: 840 | BM93: =+H93+-BL93 -> 0 | BN93: 0614-0001
A94: 46114 | B94: MCPA | F94: 108 | G94: 54 | H94: 0 | I94: =H94-G94 -> -54 | Q94: AGRIMHMCPA1L | U94: 2601059 | V94: Adolfo Almeida | W94: Zambezia | X94: Mulevala | Y94: Chiraco sede | AF94: Adolfo Almeida | AG94: 840560264 | AH94: Forencio Antonio Uatelauene | AI94: 849370189 /861682 | AM94: 260001 | BA94: -108 | BE94: =+BB94+BC94 -> 0 | BF94: =+BE94-H94 -> 0 | BG94: Sem registo | BH94: =+VLOOKUP(AF94,Sheet4!A:A,1,FALSE) -> #N/A | BL94: 0 | BM94: =+H94+-BL94 -> 0 | BN94: 0614-0001
A95: 46114 | B95: Arroz | F95: 1800 | G95: 1800 | H95: 0 | I95: =H95-G95 -> -1800 | K95: =H95/50 -> 0 | Q95: MXIXARROZKG | U95: 2601059 | V95: Adolfo Almeida | W95: Zambezia | X95: Mulevala | Y95: Chiraco sede | AF95: Adolfo Almeida | AG95: 840560264 | AH95: Forencio Antonio Uatelauene | AI95: 849370189 /861682 | AM95: 260001 | BA95: -1800 | BE95: =+BB95+BC95 -> 0 | BF95: =+BE95-H95 -> 0 | BG95: Sem registo | BH95: =+VLOOKUP(AF95,Sheet4!A:A,1,FALSE) -> #N/A | BL95: 0 | BM95: =+H95+-BL95 -> 0 | BN95: 0614-0001
A96: 46114 | B96: Feijão | F96: 2055 | G96: 2055 | H96: 420 | I96: -1635 | Q96: MXIXFEIJAOKG | U96: 2601060 | V96: Adriano Balane | W96: Maputo | X96: MAGUDE | Y96: Chichachanduco | AF96: Adriano Balane | AG96: 846035099 | AH96: Hércio Langa | AI96: 847484009 | AM96: 260001 | BE96: =+BB96+BC96 -> 0 | BF96: =+BE96-H96 -> -420 | BG96: Sem registo | BH96: =+VLOOKUP(AF96,Sheet4!A:A,1,FALSE) -> #N/A | BL96: 2055 | BM96: =+H96+-BL96 -> -1635 | BN96: 0302-0001 | BO96: Nhemba
A97: 46114 | B97: Feijão | F97: 3960 | G97: 3960 | H97: 810 | I97: -3150 | Q97: MXIXFEIJAOKG | U97: 2601060 | V97: Adriano Balane | W97: Maputo | X97: MAGUDE | Y97: Chichuco- Chichacha | AF97: Adriano Balane | AG97: 846035099 | AH97: Hércio Langa | AI97: 847484009 | AM97: 260001 | BE97: =+BB97+BC97 -> 0 | BF97: =+BE97-H97 -> -810 | BG97: Sem registo | BH97: =+VLOOKUP(AF97,Sheet4!A:A,1,FALSE) -> #N/A | BL97: 3960 | BM97: =+H97+-BL97 -> -3150 | BN97: 0302-0001 | BO97: Nhemba
A98: 46114 | B98: Feijão | F98: 2745 | G98: 2745 | H98: 570 | I98: -2175 | Q98: MXIXFEIJAOKG | U98: 2601060 | V98: Adriano Balane | W98: Maputo | X98: MAGUDE | Y98: Herois Mocambicanos | AF98: Adriano Balane | AG98: 846035099 | AH98: Hércio Langa | AI98: 847484009 | AM98: 260001 | BE98: =+BB98+BC98 -> 0 | BF98: =+BE98-H98 -> -570 | BG98: Sem registo | BH98: =+VLOOKUP(AF98,Sheet4!A:A,1,FALSE) -> #N/A | BL98: 2745 | BM98: =+H98+-BL98 -> -2175 | BN98: 0302-0001 | BO98: Nhemba
A99: 46114 | B99: Feijão | F99: 765 | G99: 765 | H99: 150 | I99: -615 | Q99: MXIXFEIJAOKG | U99: 2601060 | V99: Adriano Balane | W99: Maputo | X99: MAGUDE | Y99: Mangolene | AF99: Adriano Balane | AG99: 846035099 | AH99: Hércio Langa | AI99: 847484009 | AM99: 260001 | BE99: =+BB99+BC99 -> 0 | BF99: =+BE99-H99 -> -150 | BG99: Sem registo | BH99: =+VLOOKUP(AF99,Sheet4!A:A,1,FALSE) -> #N/A | BL99: 765 | BM99: =+H99+-BL99 -> -615 | BN99: 0302-0001 | BO99: Nhemba
A100: 46114 | B100: Feijão | F100: 735 | G100: 735 | H100: 150 | I100: -585 | Q100: MXIXFEIJAOKG | U100: 2601060 | V100: Adriano Balane | W100: Maputo | X100: MAGUDE | Y100: Muchapo | AF100: Adriano Balane | AG100: 846035099 | AH100: Hércio Langa | AI100: 847484009 | AM100: 260001 | BE100: =+BB100+BC100 -> 0 | BF100: =+BE100-H100 -> -150 | BG100: Sem registo | BH100: =+VLOOKUP(AF100,Sheet4!A:A,1,FALSE) -> #N/A | BL100: 735 | BM100: =+H100+-BL100 -> -585 | BN100: 0302-0001 | BO100: Nhemba
A101: 46114 | B101: Emamectin | F101: 137 | G101: 68.5 | H101: 28 | I101: -109 | Q101: AGRIFEMMA01L | U101: 2601060 | V101: Adriano Balane | W101: Maputo | X101: MAGUDE | Y101: Chichachanduco | AF101: Adriano Balane | AG101: 846035099 | AH101: Hércio Langa | AI101: 847484009 | AM101: 260001 | BE101: =+BB101+BC101 -> 0 | BF101: =+BE101-H101 -> -28 | BG101: Sem registo | BH101: =+VLOOKUP(AF101,Sheet4!A:A,1,FALSE) -> #N/A | BL101: 68.5 | BM101: =+H101+-BL101 -> -40.5 | BN101: 0302-0001
A102: 46114 | B102: Emamectin | F102: 264 | G102: 132 | H102: 54 | I102: -210 | Q102: AGRIFEMMA01L | U102: 2601060 | V102: Adriano Balane | W102: Maputo | X102: MAGUDE | Y102: Chichuco- Chichacha | AF102: Adriano Balane | AG102: 846035099 | AH102: Hércio Langa | AI102: 847484009 | AM102: 260001 | BE102: =+BB102+BC102 -> 0 | BF102: =+BE102-H102 -> -54 | BG102: Sem registo | BH102: =+VLOOKUP(AF102,Sheet4!A:A,1,FALSE) -> #N/A | BL102: 132 | BM102: =+H102+-BL102 -> -78 | BN102: 0302-0001
A103: 46114 | B103: Emamectin | F103: 183 | G103: 91.5 | H103: 38 | I103: -145 | Q103: AGRIFEMMA01L | U103: 2601060 | V103: Adriano Balane | W103: Maputo | X103: MAGUDE | Y103: Herois Mocambicanos | AF103: Adriano Balane | AG103: 846035099 | AH103: Hércio Langa | AI103: 847484009 | AM103: 260001 | BE103: =+BB103+BC103 -> 0 | BF103: =+BE103-H103 -> -38 | BG103: Sem registo | BH103: =+VLOOKUP(AF103,Sheet4!A:A,1,FALSE) -> #N/A | BL103: 91.5 | BM103: =+H103+-BL103 -> -53.5 | BN103: 0302-0001
A104: 46114 | B104: Emamectin | F104: 51 | G104: 25.5 | H104: 10 | I104: -41 | Q104: AGRIFEMMA01L | U104: 2601060 | V104: Adriano Balane | W104: Maputo | X104: MAGUDE | Y104: Mangolene | AF104: Adriano Balane | AG104: 846035099 | AH104: Hércio Langa | AI104: 847484009 | AM104: 260001 | BE104: =+BB104+BC104 -> 0 | BF104: =+BE104-H104 -> -10 | BG104: Sem registo | BH104: =+VLOOKUP(AF104,Sheet4!A:A,1,FALSE) -> #N/A | BL104: 25.5 | BM104: =+H104+-BL104 -> -15.5 | BN104: 0302-0001
A105: 46114 | B105: Emamectin | F105: 49 | G105: 24.5 | H105: 10 | I105: -39 | Q105: AGRIFEMMA01L | U105: 2601060 | V105: Adriano Balane | W105: Maputo | X105: MAGUDE | Y105: Muchapo | AF105: Adriano Balane | AG105: 846035099 | AH105: Hércio Langa | AI105: 847484009 | AM105: 260001 | BE105: =+BB105+BC105 -> 0 | BF105: =+BE105-H105 -> -10 | BG105: Sem registo | BH105: =+VLOOKUP(AF105,Sheet4!A:A,1,FALSE) -> #N/A | BL105: 24.5 | BM105: =+H105+-BL105 -> -14.5 | BN105: 0302-0001
A106: 46114 | B106: Sacos Hermeticos | F106: 2740 | G106: 2740 | H106: 560 | I106: -2180 | Q106: SUSSACO | U106: 2601060 | V106: Adriano Balane | W106: Maputo | X106: MAGUDE | Y106: Chichachanduco | AF106: Adriano Balane | AG106: 846035099 | AH106: Hércio Langa | AI106: 847484009 | AM106: 260001 | BE106: =+BB106+BC106 -> 0 | BF106: =+BE106-H106 -> -560 | BG106: Sem registo | BH106: =+VLOOKUP(AF106,Sheet4!A:A,1,FALSE) -> #N/A | BL106: 2740 | BM106: =+H106+-BL106 -> -2180 | BN106: 0302-0001
A107: 46114 | B107: Sacos Hermeticos | F107: 5280 | G107: 5280 | H107: 1080 | I107: -4200 | Q107: SUSSACO | U107: 2601060 | V107: Adriano Balane | W107: Maputo | X107: MAGUDE | Y107: Chichuco- Chichacha | AF107: Adriano Balane | AG107: 846035099 | AH107: Hércio Langa | AI107: 847484009 | AM107: 260001 | BE107: =+BB107+BC107 -> 0 | BF107: =+BE107-H107 -> -1080 | BG107: Sem registo | BH107: =+VLOOKUP(AF107,Sheet4!A:A,1,FALSE) -> #N/A | BL107: 5280 | BM107: =+H107+-BL107 -> -4200 | BN107: 0302-0001
A108: 46114 | B108: Sacos Hermeticos | F108: 3660 | G108: 3660 | H108: 760 | I108: -2900 | Q108: SUSSACO | U108: 2601060 | V108: Adriano Balane | W108: Maputo | X108: MAGUDE | Y108: Herois Mocambicanos | AF108: Adriano Balane | AG108: 846035099 | AH108: Hércio Langa | AI108: 847484009 | AM108: 260001 | BE108: =+BB108+BC108 -> 0 | BF108: =+BE108-H108 -> -760 | BG108: Sem registo | BH108: =+VLOOKUP(AF108,Sheet4!A:A,1,FALSE) -> #N/A | BL108: 3660 | BM108: =+H108+-BL108 -> -2900 | BN108: 0302-0001
A109: 46114 | B109: Sacos Hermeticos | F109: 1020 | G109: 1020 | H109: 200 | I109: -820 | Q109: SUSSACO | U109: 2601060 | V109: Adriano Balane | W109: Maputo | X109: MAGUDE | Y109: Mangolene | AF109: Adriano Balane | AG109: 846035099 | AH109: Hércio Langa | AI109: 847484009 | AM109: 260001 | BE109: =+BB109+BC109 -> 0 | BF109: =+BE109-H109 -> -200 | BG109: Sem registo | BH109: =+VLOOKUP(AF109,Sheet4!A:A,1,FALSE) -> #N/A | BL109: 1020 | BM109: =+H109+-BL109 -> -820 | BN109: 0302-0001
A110: 46114 | B110: Sacos Hermeticos | F110: 980 | G110: 980 | H110: 200 | I110: -780 | Q110: SUSSACO | U110: 2601060 | V110: Adriano Balane | W110: Maputo | X110: MAGUDE | Y110: Muchapo | AF110: Adriano Balane | AG110: 846035099 | AH110: Hércio Langa | AI110: 847484009 | AM110: 260001 | BE110: =+BB110+BC110 -> 0 | BF110: =+BE110-H110 -> -200 | BG110: Sem registo | BH110: =+VLOOKUP(AF110,Sheet4!A:A,1,FALSE) -> #N/A | BL110: 980 | BM110: =+H110+-BL110 -> -780 | BN110: 0302-0001
A111: 46114 | B111: Imadocloprid | F111: 137 | G111: 68.5 | H111: 28 | I111: -109 | Q111: AGRIMIDACLORP1L | U111: 2601060 | V111: Adriano Balane | W111: Maputo | X111: MAGUDE | Y111: Chichachanduco | AF111: Adriano Balane | AG111: 846035099 | AH111: Hércio Langa | AI111: 847484009 | AM111: 260001 | BE111: =+BB111+BC111 -> 0 | BF111: =+BE111-H111 -> -28 | BG111: Sem registo | BH111: =+VLOOKUP(AF111,Sheet4!A:A,1,FALSE) -> #N/A | BL111: 68.5 | BM111: =+H111+-BL111 -> -40.5 | BN111: 0302-0001
...

Sheet Sheet4
A1: Berto Macino Chicico
A2: Carlos Roque Quembo
A3: Denilson Manuel Couve
A4: Denilson Manuel Couve
A5: Elisa Sarifo Sunzumua
A6: Elton Vasco Luisse
A7: Filipe Paulino Saute
A8: Helder Zunguze
A9: Helio Joao Manidide Sigauque
A10: Isaak Castrim Jossefa
A11: Isaquiel A. C. Meque
A12: Issa Pedro Aguiar
... A27: Zito Mario Abage

Sheet Totais por Província
A1: Província | B1: Antes (Planificado) | E1: Depois (Actualizado) | H1: Variação
A2: Província | B2: Kit 1 | C2: Kit 2 | D2: Total | E2: Kit 1 | F2: Kit 2 | G2: Total | H2: Kit 1 | I2: Kit 2 | J2: Total
A3: Maputo | B3: 15930 | C3: 1970 | D3: =B3+C3 -> 17900 | E3: sem dados | F3: sem dados | G3: sem dados | H3: sem dados | I3: sem dados | J3: sem dados
A4: Gaza | B4: 66676 | C4: 8756 | D4: =B4+C4 -> 75432 | E4: sem dados | F4: sem dados | G4: sem dados | H4: sem dados | I4: sem dados | J4: sem dados
A5: Sofala | B5: 27181 | C5: 11307 | D5: =B5+C5 -> 38488 | E5: 12194 | F5: 5201 | G5: =E5+F5 -> 17395 | H5: =E5-B5 -> -14987 | I5: =F5-C5 -> -6106 | J5: =G5-D5 -> -21093
A6: Zambezia | B6: 7810 | C6: 4175 | D6: =B6+C6 -> 11985 | E6: 3676 | F6: 1607 | G6: =E6+F6 -> 5283 | H6: =E6-B6 -> -4134 | I6: =F6-C6 -> -2568 | J6: =G6-D6 -> -6702
A7: Manica | B7: 7554 | C7: 0 | D7: =B7+C7 -> 7554 | E7: 2230 | F7: 0 | G7: =E7+F7 -> 2230 | H7: =E7-B7 -> -5324 | I7: =F7-C7 -> 0 | J7: =G7-D7 -> -5324
A8: Tete | B8: 6079 | C8: 1258 | D8: =B8+C8 -> 7337 | E8: 3316 | F8: 20 | G8: =E8+F8 -> 3336 | H8: =E8-B8 -> -2763 | I8: =F8-C8 -> -1238 | J8: =G8-D8 -> -4001
A9: TOTAL GERAL | B9: =SUM(B3:B8) -> 131230 | C9: =SUM(C3:C8) -> 27466 | D9: =SUM(D3:D8) -> 158696 | E9: =SUM(E3:E8) -> 21416 | F9: =SUM(F3:F8) -> 6828 | G9: =SUM(G3:G8) -> 28244 | H9: =SUM(H3:H8) -> -27208 | I9: =SUM(I3:I8) -> -9912 | J9: =SUM(J3:J8) -> -37120
A11: Notas:
A12: • 'Depois' inclui novos extensionistas inseridos pelas equipas provinciais (ver 'Novos Beneficiários').
A13: • Maputo e Gaza ainda sem listas actualizadas.

Sheet Necessidades por Província
A1: Necessidades de Insumos por Província
A3: Província | B3: Antes | E3: Depois
A4: Província | B4: Kit 1 | C4: Kit 2 | D4: Total | E4: Kit 1 | F4: Kit 2 | G4: Total
A5: Maputo | B5: 15930 | C5: 1970 | D5: =B5+C5 -> 17900 | E5: sem dados | F5: sem dados | G5: sem dados
A6: Gaza | B6: 66676 | C6: 8756 | D6: =B6+C6 -> 75432 | E6: sem dados | F6: sem dados | G6: sem dados
A7: Sofala | B7: 27181 | C7: 11307 | D7: =B7+C7 -> 38488 | E7: 12194 | F7: 5201 | G7: =E7+F7 -> 17395
A8: Zambezia | B8: 7810 | C8: 4175 | D8: =B8+C8 -> 11985 | E8: 3676 | F8: 1607 | G8: =E8+F8 -> 5283
A9: Manica | B9: 7554 | C9: 0 | D9: =B9+C9 -> 7554 | E9: 2230 | F9: 0 | G9: =E9+F9 -> 2230
A10: Tete | B10: 6079 | C10: 1258 | D10: =B10+C10 -> 7337 | E10: 3316 | F10: 20 | G10: =E10+F10 -> 3336
A11: TOTAL | B11: =SUM(B5:B10) -> 131230 | C11: =SUM(C5:C10) -> 27466 | D11: =SUM(D5:D10) -> 158696 | E11: =SUM(E5:E10) -> 21416 | F11: =SUM(F5:F10) -> 6828 | G11: =SUM(G5:G10) -> 28244
A14: Necessidades totais de insumos
A15: Insumo | B15: Unidade | C15: Maputo | F15: Gaza | I15: Sofala | L15: Zambezia | O15: Manica | R15: Tete | U15: TOTAL
C16: Antes | D16: Depois | E16: Variação | F16: Antes | G16: Depois | H16: Variação | I16: Antes | J16: Depois | K16: Variação | L16: Antes | M16: Depois | N16: Variação | O16: Antes | P16: Depois | Q16: Variação | R16: Antes | S16: Depois | T16: Variação | U16: Antes | V16: Depois | W16: Variação
A17: Milho | B17: Kg | C17: =IFERROR(B5*'Composição dos Kits'!C4+C5*'Composição dos Kits'!D4,0) -> 199125 | F17: =IFERROR(B6*'Composição dos Kits'!C4+C6*'Composição dos Kits'!D4,0) -> 833450 | I17: =IFERROR(B7*'Composição dos Kits'!C4+C7*'Composição dos Kits'!D4,0) -> 339762.5 | J17: =IFERROR(E7*'Composição dos Kits'!C4+F7*'Composição dos Kits'!D4,0) -> 152425 | K17: =J17-I17 -> -187337.5 | L17: =IFERROR(B8*'Composição dos Kits'!C4+C8*'Composição dos Kits'!D4,0) -> 97625 | M17: =IFERROR(E8*'Composição dos Kits'!C4+F8*'Composição dos Kits'!D4,0) -> 45950 | N17: =M17-L17 -> -51675 | O17: =IFERROR(B9*'Composição dos Kits'!C4+C9*'Composição dos Kits'!D4,0) -> 94425 | P17: =IFERROR(E9*'Composição dos Kits'!C4+F9*'Composição dos Kits'!D4,0) -> 27875 | Q17: =P17-O17 -> -66550 | R17: =IFERROR(B10*'Composição dos Kits'!C4+C10*'Composição dos Kits'!D4,0) -> 75987.5 | S17: =IFERROR(E10*'Composição dos Kits'!C4+F10*'Composição dos Kits'!D4,0) -> 41450 | T17: =S17-R17 -> -34537.5 | U17: =C17+F17+I17+L17+O17+R17 -> 1640375 | V17: =SUM(D17,G17,J17,M17,P17,S17) -> 267700 | W17: =V17-U17 -> -1372675
A18: Arroz | B18: Kg | C18: =IFERROR(B5*'Composição dos Kits'!C5+C5*'Composição dos Kits'!D5,0) -> 98500 | F18: =IFERROR(B6*'Composição dos Kits'!C5+C6*'Composição dos Kits'!D5,0) -> 437800 | I18: =IFERROR(B7*'Composição dos Kits'!C5+C7*'Composição dos Kits'!D5,0) -> 565350 | J18: =IFERROR(E7*'Composição dos Kits'!C5+F7*'Composição dos Kits'!D5,0) -> 260050 | K18: =J18-I18 -> -305300 | L18: =IFERROR(B8*'Composição dos Kits'!C5+C8*'Composição dos Kits'!D5,0) -> 208750 | M18: =IFERROR(E8*'Composição dos Kits'!C5+F8*'Composição dos Kits'!D5,0) -> 80350 | N18: =M18-L18 -> -128400 | O18: =IFERROR(B9*'Composição dos Kits'!C5+C9*'Composição dos Kits'!D5,0) -> 0 | P18: =IFERROR(E9*'Composição dos Kits'!C5+F9*'Composição dos Kits'!D5,0) -> 0 | Q18: =P18-O18 -> 0 | R18: =IFERROR(B10*'Composição dos Kits'!C5+C10*'Composição dos Kits'!D5,0) -> 62900 | S18: =IFERROR(E10*'Composição dos Kits'!C5+F10*'Composição dos Kits'!D5,0) -> 1000 | T18: =S18-R18 -> -61900 | U18: =C18+F18+I18+L18+O18+R18 -> 1373300 | V18: =SUM(D18,G18,J18,M18,P18,S18) -> 341400 | W18: =V18-U18 -> -1031900
A19: Feijão Vulgar | B19: Kg | C19: =IFERROR(B5*'Composição dos Kits'!C6+C5*'Composição dos Kits'!D6,0) -> 268500 | F19: =IFERROR(B6*'Composição dos Kits'!C6+C6*'Composição dos Kits'!D6,0) -> 1131480 | I19: =IFERROR(B7*'Composição dos Kits'!C6+C7*'Composição dos Kits'!D6,0) -> 577320 | J19: =IFERROR(E7*'Composição dos Kits'!C6+F7*'Composição dos Kits'!D6,0) -> 260925 | K19: =J19-I19 -> -316395 | L19: =IFERROR(B8*'Composição dos Kits'!C6+C8*'Composição dos Kits'!D6,0) -> 179775 | M19: =IFERROR(E8*'Composição dos Kits'!C6+F8*'Composição dos Kits'!D6,0) -> 79245 | N19: =M19-L19 -> -100530 | O19: =IFERROR(B9*'Composição dos Kits'!C6+C9*'Composição dos Kits'!D6,0) -> 113310 | P19: =IFERROR(E9*'Composição dos Kits'!C6+F9*'Composição dos Kits'!D6,0) -> 33450 | Q19: =P19-O19 -> -79860 | R19: =IFERROR(B10*'Composição dos Kits'!C6+C10*'Composição dos Kits'!D6,0) -> 110055 | S19: =IFERROR(E10*'Composição dos Kits'!C6+F10*'Composição dos Kits'!D6,0) -> 50040 | T19: =S19-R19 -> -60015 | U19: =C19+F19+I19+L19+O19+R19 -> 2380440 | V19: =SUM(D19,G19,J19,M19,P19,S19) -> 423660 | W19: =V19-U19 -> -1956780
A20: Couve | B20: g | C20: =IFERROR(B5*'Composição dos Kits'!C7+C5*'Composição dos Kits'!D7,0) -> 179000 | F20: =IFERROR(B6*'Composição dos Kits'!C7+C6*'Composição dos Kits'!D7,0) -> 754320 | I20: =IFERROR(B7*'Composição dos Kits'!C7+C7*'Composição dos Kits'!D7,0) -> 384880 | J20: =IFERROR(E7*'Composição dos Kits'!C7+F7*'Composição dos Kits'!D7,0) -> 173950 | K20: =J20-I20 -> -210930 | L20: =IFERROR(B8*'Composição dos Kits'!C7+C8*'Composição dos Kits'!D7,0) -> 119850 | M20: =IFERROR(E8*'Composição dos Kits'!C7+F8*'Composição dos Kits'!D7,0) -> 52830 | N20: =M20-L20 -> -67020 | O20: =IFERROR(B9*'Composição dos Kits'!C7+C9*'Composição dos Kits'!D7,0) -> 75540 | P20: =IFERROR(E9*'Composição dos Kits'!C7+F9*'Composição dos Kits'!D7,0) -> 22300 | Q20: =P20-O20 -> -53240 | R20: =IFERROR(B10*'Composição dos Kits'!C7+C10*'Composição dos Kits'!D7,0) -> 73370 | S20: =IFERROR(E10*'Composição dos Kits'!C7+F10*'Composição dos Kits'!D7,0) -> 33360 | T20: =S20-R20 -> -40010 | U20: =C20+F20+I20+L20+O20+R20 -> 1586960 | V20: =SUM(D20,G20,J20,M20,P20,S20) -> 282440 | W20: =V20-U20 -> -1304520
A21: Alface | B21: g | C21: =IFERROR(B5*'Composição dos Kits'!C8+C5*'Composição dos Kits'!D8,0) -> 179000 | F21: =IFERROR(B6*'Composição dos Kits'!C8+C6*'Composição dos Kits'!D8,0) -> 754320 | I21: =IFERROR(B7*'Composição dos Kits'!C8+C7*'Composição dos Kits'!D8,0) -> 384880 | J21: =IFERROR(E7*'Composição dos Kits'!C8+F7*'Composição dos Kits'!D8,0) -> 173950 | K21: =J21-I21 -> -210930 | L21: =IFERROR(B8*'Composição dos Kits'!C8+C8*'Composição dos Kits'!D8,0) -> 119850 | M21: =IFERROR(E8*'Composição dos Kits'!C8+F8*'Composição dos Kits'!D8,0) -> 52830 | N21: =M21-L21 -> -67020 | O21: =IFERROR(B9*'Composição dos Kits'!C8+C9*'Composição dos Kits'!D8,0) -> 75540 | P21: =IFERROR(E9*'Composição dos Kits'!C8+F9*'Composição dos Kits'!D8,0) -> 22300 | Q21: =P21-O21 -> -53240 | R21: =IFERROR(B10*'Composição dos Kits'!C8+C10*'Composição dos Kits'!D8,0) -> 73370 | S21: =IFERROR(E10*'Composição dos Kits'!C8+F10*'Composição dos Kits'!D8,0) -> 33360 | T21: =S21-R21 -> -40010 | U21: =C21+F21+I21+L21+O21+R21 -> 1586960 | V21: =SUM(D21,G21,J21,M21,P21,S21) -> 282440 | W21: =V21-U21 -> -1304520
A22: NPK 12.24.12 | B22: Kg | C22: =IFERROR(B5*'Composição dos Kits'!C9+C5*'Composição dos Kits'!D9,0) -> 895000 | F22: =IFERROR(B6*'Composição dos Kits'!C9+C6*'Composição dos Kits'!D9,0) -> 3771600 | I22: =IFERROR(B7*'Composição dos Kits'!C9+C7*'Composição dos Kits'!D9,0) -> 1924400 | J22: =IFERROR(E7*'Composição dos Kits'!C9+F7*'Composição dos Kits'!D9,0) -> 869750 | K22: =J22-I22 -> -1054650 | L22: =IFERROR(B8*'Composição dos Kits'!C9+C8*'Composição dos Kits'!D9,0) -> 599250 | M22: =IFERROR(E8*'Composição dos Kits'!C9+F8*'Composição dos Kits'!D9,0) -> 264150 | N22: =M22-L22 -> -335100 | O22: =IFERROR(B9*'Composição dos Kits'!C9+C9*'Composição dos Kits'!D9,0) -> 377700 | P22: =IFERROR(E9*'Composição dos Kits'!C9+F9*'Composição dos Kits'!D9,0) -> 111500 | Q22: =P22-O22 -> -266200 | R22: =IFERROR(B10*'Composição dos Kits'!C9+C10*'Composição dos Kits'!D9,0) -> 366850 | S22: =IFERROR(E10*'Composição dos Kits'!C9+F10*'Composição dos Kits'!D9,0) -> 166800 | T22: =S22-R22 -> -200050 | U22: =C22+F22+I22+L22+O22+R22 -> 7934800 | V22: =SUM(D22,G22,J22,M22,P22,S22) -> 1412200 | W22: =V22-U22 -> -6522600
A23: Enxada | B23: un | C23: =IFERROR(B5*'Composição dos Kits'!C10+C5*'Composição dos Kits'!D10,0) -> 17900 | F23: =IFERROR(B6*'Composição dos Kits'!C10+C6*'Composição dos Kits'!D10,0) -> 75432 | I23: =IFERROR(B7*'Composição dos Kits'!C10+C7*'Composição dos Kits'!D10,0) -> 38488 | J23: =IFERROR(E7*'Composição dos Kits'!C10+F7*'Composição dos Kits'!D10,0) -> 17395 | K23: =J23-I23 -> -21093 | L23: =IFERROR(B8*'Composição dos Kits'!C10+C8*'Composição dos Kits'!D10,0) -> 11985 | M23: =IFERROR(E8*'Composição dos Kits'!C10+F8*'Composição dos Kits'!D10,0) -> 5283 | N23: =M23-L23 -> -6702 | O23: =IFERROR(B9*'Composição dos Kits'!C10+C9*'Composição dos Kits'!D10,0) -> 7554 | P23: =IFERROR(E9*'Composição dos Kits'!C10+F9*'Composição dos Kits'!D10,0) -> 2230 | Q23: =P23-O23 -> -5324 | R23: =IFERROR(B10*'Composição dos Kits'!C10+C10*'Composição dos Kits'!D10,0) -> 7337 | S23: =IFERROR(E10*'Composição dos Kits'!C10+F10*'Composição dos Kits'!D10,0) -> 3336 | T23: =S23-R23 -> -4001 | U23: =C23+F23+I23+L23+O23+R23 -> 158696 | V23: =SUM(D23,G23,J23,M23,P23,S23) -> 28244 | W23: =V23-U23 -> -130452
A24: Emamectim Benzoato | B24: L | C24: =IFERROR(B5*'Composição dos Kits'!C11+C5*'Composição dos Kits'!D11,0) -> 8950 | F24: =IFERROR(B6*'Composição dos Kits'!C11+C6*'Composição dos Kits'!D11,0) -> 37716 | I24: =IFERROR(B7*'Composição dos Kits'!C11+C7*'Composição dos Kits'!D11,0) -> 19244 | J24: =IFERROR(E7*'Composição dos Kits'!C11+F7*'Composição dos Kits'!D11,0) -> 8697.5 | K24: =J24-I24 -> -10546.5 | L24: =IFERROR(B8*'Composição dos Kits'!C11+C8*'Composição dos Kits'!D11,0) -> 5992.5 | M24: =IFERROR(E8*'Composição dos Kits'!C11+F8*'Composição dos Kits'!D11,0) -> 2641.5 | N24: =M24-L24 -> -3351 | O24: =IFERROR(B9*'Composição dos Kits'!C11+C9*'Composição dos Kits'!D11,0) -> 3777 | P24: =IFERROR(E9*'Composição dos Kits'!C11+F9*'Composição dos Kits'!D11,0) -> 1115 | Q24: =P24-O24 -> -2662 | R24: =IFERROR(B10*'Composição dos Kits'!C11+C10*'Composição dos Kits'!D11,0) -> 3668.5 | S24: =IFERROR(E10*'Composição dos Kits'!C11+F10*'Composição dos Kits'!D11,0) -> 1668 | T24: =S24-R24 -> -2000.5 | U24: =C24+F24+I24+L24+O24+R24 -> 79348 | V24: =SUM(D24,G24,J24,M24,P24,S24) -> 14122 | W24: =V24-U24 -> -65226
A25: Imidacloprid | B25: L | C25: =IFERROR(B5*'Composição dos Kits'!C12+C5*'Composição dos Kits'!D12,0) -> 7965 | F25: =IFERROR(B6*'Composição dos Kits'!C12+C6*'Composição dos Kits'!D12,0) -> 33338 | I25: =IFERROR(B7*'Composição dos Kits'!C12+C7*'Composição dos Kits'!D12,0) -> 13590.5 | J25: =IFERROR(E7*'Composição dos Kits'!C12+F7*'Composição dos Kits'!D12,0) -> 6097 | K25: =J25-I25 -> -7493.5 | L25: =IFERROR(B8*'Composição dos Kits'!C12+C8*'Composição dos Kits'!D12,0) -> 3905 | M25: =IFERROR(E8*'Composição dos Kits'!C12+F8*'Composição dos Kits'!D12,0) -> 1838 | N25: =M25-L25 -> -2067 | O25: =IFERROR(B9*'Composição dos Kits'!C12+C9*'Composição dos Kits'!D12,0) -> 3777 | P25: =IFERROR(E9*'Composição dos Kits'!C12+F9*'Composição dos Kits'!D12,0) -> 1115 | Q25: =P25-O25 -> -2662 | R25: =IFERROR(B10*'Composição dos Kits'!C12+C10*'Composição dos Kits'!D12,0) -> 3039.5 | S25: =IFERROR(E10*'Composição dos Kits'!C12+F10*'Composição dos Kits'!D12,0) -> 1658 | T25: =S25-R25 -> -1381.5 | U25: =C25+F25+I25+L25+O25+R25 -> 65615 | V25: =SUM(D25,G25,J25,M25,P25,S25) -> 10708 | W25: =V25-U25 -> -54907
A26: MCPA | B26: L | C26: =IFERROR(B5*'Composição dos Kits'!C13+C5*'Composição dos Kits'!D13,0) -> 2955 | F26: =IFERROR(B6*'Composição dos Kits'!C13+C6*'Composição dos Kits'!D13,0) -> 13134 | I26: =IFERROR(B7*'Composição dos Kits'!C13+C7*'Composição dos Kits'!D13,0) -> 16960.5 | J26: =IFERROR(E7*'Composição dos Kits'!C13+F7*'Composição dos Kits'!D13,0) -> 7801.5 | K26: =J26-I26 -> -9159 | L26: =IFERROR(B8*'Composição dos Kits'!C13+C8*'Composição dos Kits'!D13,0) -> 6262.5 | M26: =IFERROR(E8*'Composição dos Kits'!C13+F8*'Composição dos Kits'!D13,0) -> 2410.5 | N26: =M26-L26 -> -3852 | O26: =IFERROR(B9*'Composição dos Kits'!C13+C9*'Composição dos Kits'!D13,0) -> 0 | P26: =IFERROR(E9*'Composição dos Kits'!C13+F9*'Composição dos Kits'!D13,0) -> 0 | Q26: =P26-O26 -> 0 | R26: =IFERROR(B10*'Composição dos Kits'!C13+C10*'Composição dos Kits'!D13,0) -> 1887 | S26: =IFERROR(E10*'Composição dos Kits'!C13+F10*'Composição dos Kits'!D13,0) -> 30 | T26: =S26-R26 -> -1857 | U26: =C26+F26+I26+L26+O26+R26 -> 41199 | V26: =SUM(D26,G26,J26,M26,P26,S26) -> 10242 | W26: =V26-U26 -> -30957

Sheet Novos Beneficiários
A1: Extensionist ID | B1: Extensionista | C1: Contacto Extensionista | D1: Supervisor | E1: Contacto Supervisor | F1: Província | G1: Distrito | H1: Localidade | I1: Kit | J1: Qtd Anterior | K1: Qtd Actualizada | L1: Variação
A2: 0210-0002 | B2: Chenguetai Quichine | C2: 862441603 | D2: Felizardo Constantino Chicoche | E2: 861948841 | F2: Manica | G2: Barue | H2: Chuala | I2: Kit 1 | J2: 0 | K2: 13 | L2: 13
A3: 0210-0003 | B3: Daniel J.F.Paulo | C3: 863413681 | D3: Felizardo Constantino Chicoche | E3: 861948841 | F3: Manica | G3: Barue | H3: Nhabuto | I3: Kit 1 | J3: 0 | K3: 14 | L3: 14
A4: 0210-0004 | B4: Francisca C. Roia | C4: 861570229 | D4: Felizardo Constantino Chicoche | E4: 861948841 | F4: Manica | G4: Barue | H4: Nfudze | I4: Kit 1 | J4: 0 | K4: 8 | L4: 8
A5: 0210-0005 | B5: Gimmy Cliffy Narcisio | C5: 847244778 | D5: Felizardo Constantino Chicoche | E5: 861948841 | F5: Manica | G5: Barue | H5: Inhazonia | I5: Kit 1 | J5: 0 | K5: 13 | L5: 13
A6: 0210-0006 | B6: Isabel Luis Mario | C6: 873392617 | D6: Felizardo Constantino Chicoche | E6: 861948841 | F6: Manica | G6: Barue | H6: Inhazonia | I6: Kit 1 | J6: 0 | K6: 19 | L6: 19
A7: 0210-0007 | B7: Joaquim José Simão | C7: 860289921 | D7: Felizardo Constantino Chicoche | E7: 861948841 | F7: Manica | G7: Barue | H7: Chuala | I7: Kit 1 | J7: 0 | K7: 18 | L7: 18
A8: 0210-0008 | B8: Joelmo Francisco | C8: 872763746 | D8: Felizardo Constantino Chicoche | E8: 861948841 | F8: Manica | G8: Barue | H8: Catandica | I8: Kit 1 | J8: 0 | K8: 32 | L8: 32
A9: 0210-0009 | B9: Lucas Jose Mussosso | C9: 865082456 | D9: Felizardo Constantino Chicoche | E9: 861948841 | F9: Manica | G9: Barue | H9: Honde sede | I9: Kit 1 | J9: 0 | K9: 12 | L9: 12
A10: 0210-0010 | B10: Mugabe G. Monteiro | C10: 878727342 | D10: Felizardo Constantino Chicoche | E10: 861948841 | F10: Manica | G10: Barue | H10: Chuala | I10: Kit 1 | J10: 0 | K10: 13 | L10: 13
A11: 0210-0011 | B11: Rui Banqueiro | C11: 846867468 | D11: Felizardo Constantino Chicoche | E11: 861948841 | F11: Manica | G11: Barue | H11: Chuala | I11: Kit 1 | J11: 0 | K11: 11 | L11: 11
A12: 0210-0012 | B12: Tomas Samuel Lázaro | C12: 842696591 | D12: Felizardo Constantino Chicoche | E12: 861948841 | F12: Manica | G12: Barue | H12: Nhassacara | I12: Kit 1 | J12: 0 | K12: 13 | L12: 13
A13: 0211-0002 | B13: Aminosse Lucas licosso | C13: 845490249 | D13: Esmael Gonsalvez Pinto | E13: 878173978 | F13: Manica | G13: Machaze | H13: Sambassoca | I13: Kit 1 | J13: 0 | K13: 1 | L13: 1
... A105: 0510-0007 | B105: Terio Fevereiro Semente | C105: 862409932 | D105: Jerson Francisco Saguate | E105: 873584824 | F105: Tete | G105: Chifunde | H105: Nsadzu Sede | I105: Kit 1 | J105: 0 | K105: 11 | L105: 11
A106: 0511-0001 | B106: Bonifácio Frederico Maferano | C106: 857018425 | D106: Rosa Chioi | E106: 822202505 | F106: Tete | G106: Cidade de Tete | I106: Kit 1 | J106: 0 | K106: 96 | L106: 96
A107: 0511-0002 | B107: Cláudio Francisco Presente | C107: 848021417 | D107: Rosa Chioi | E107: 822202505 | F107: Tete | G107: Cidade de Tete | I107: Kit 1 | J107: 0 | K107: 47 | L107: 47
A108: 0511-0003 | B108: Dudú Januário Júlio | C108: 844747713 | D108: Rosa Chioi | E108: 822202505 | F108: Tete | G108: Cidade de Tete | I108: Kit 1 | J108: 0 | K108: 47 | L108: 47
A109: 0511-0004 | B109: Inês Vasco Balanca | C109: 873189788 | D109: Rosa Chioi | E109: 822202505 | F109: Tete | G109: Cidade de Tete | I109: Kit 1 | J109: 0 | K109: 47 | L109: 47
A110: 0511-0005 | B110: Lia Manuel Mapolissa | C110: 847321638 | D110: Rosa Chioi | E110: 822202505 | F110: Tete | G110: Cidade de Tete | I110: Kit 1 | J110: 0 | K110: 48 | L110: 48
A111: 0511-0006 | B111: Rosa Chioi | C111: 822202505 | D111: Rosa Chioi | E111: 822202505 | F111: Tete | G111: Cidade de Tete | I111: Kit 1 | J111: 0 | K111: 15 | L111: 15
A112: 0504-0005 | B112: Adelia Eduardo | C112: 867346208 | D112: Ester Domingos Reis | E112: 866993712 | F112: Tete | G112: Doa | H112: Chueza | I112: Kit 1 | J112: 0 | K112: 77 | L112: 77
A113: 0504-0006 | B113: Almirante Augusto | C113: 867246140 | D113: Ester Domingos Reis | E113: 866993712 | F113: Tete | G113: Doa | H113: Salima | I113: Kit 1 | J113: 0 | K113: 55 | L113: 55
A114: 0504-0007 | B114: Anita Domingos | C114: 8634495223 | D114: Ester Domingos Reis | E114: 866993712 | F114: Tete | G114: Doa | H114: Salima | I114: Kit 1 | J114: 0 | K114: 40 | L114: 40
A115: 0504-0008 | B115: Gervasio Rodrigues | C115: 873901527 | D115: Ester Domingos Reis | E115: 866993712 | F115: Tete | G115: Doa | H115: Doa-Sede | I115: Kit 1 | J115: 0 | K115: 35 | L115: 35
A116: 0512-0001 | B116: Anita António Felisberto João | C116: 877961829 | D116: Juma Pedro Simital | E116: 862155221 | F116: Tete | G116: Macanga | H116: Namadende | I116: Kit 1 | J116: 0 | K116: 5 | L116: 5
A117: 0512-0002 | B117: Elsa Stella António | C117: 840501282 | D117: Juma Pedro Simital | E117: 862155221 | F117: Tete | G117: Macanga | H117: Furancungo | I117: Kit 1 | J117: 0 | K117: 19 | L117: 19
A118: 0512-0003 | B118: Faustino Inácio Almoço João | C118: 860555303 | D118: Juma Pedro Simital | E118: 862155221 | F118: Tete | G118: Macanga | H118: Furancungo | I118: Kit 1 | J118: 0 | K118: 3 | L118: 3
A119: 0512-0004 | B119: Quito Albino Sande | C119: 864694802 | D119: Juma Pedro Simital | E119: 862155221 | F119: Tete | G119: Macanga | H119: Báuè | I119: Kit 1 | J119: 0 | K119: 1 | L119: 1
A120: 0512-0005 | B120: Tania Francisco | C120: 879221061 | D120: Juma Pedro Simital | E120: 862155221 | F120: Tete | G120: Macanga | H120: Gandali | I120: Kit 1 | J120: 0 | K120: 5 | L120: 5
A121: 0512-0006 | B121: Titos Francisco Tomas | C121: 879959161 | D121: Juma Pedro Simital | E121: 862155221 | F121: Tete | G121: Macanga | H121: Gandali | I121: Kit 1 | J121: 0 | K121: 3 | L121: 3
A122: 0512-0007 | B122: Verónica Geremias Mateus Ramucesse | C122: 876298744 | D122: Juma Pedro Simital | E122: 862155221 | F122: Tete | G122: Macanga | H122: Campala | I122: Kit 1 | J122: 0 | K122: 5 | L122: 5
A123: 0512-0008 | B123: Wilson Lucas Petroce | C123: 863026920 | D123: Juma Pedro Simital | E123: 862155221 | F123: Tete | G123: Macanga | H123: Campala | I123: Kit 1 | J123: 0 | K123: 9 | L123: 9
... A135: 0506-0005 | B135: Herminio Vasco | C135: 878814519 | D135: Bernardo Xavier Jojo | E135: 865438512 | F135: Tete | G135: Moatize | H135: Mpandzu | I135: Kit 1 | J135: 0 | K135: 100 | L135: 100
B136: Sem nome 1 | D136: Bernardo Xavier Jojo | E136: 865438512 | F136: Tete | G136: Moatize | H136: Ntsungo | I136: Kit 1 | J136: 0 | K136: 1 | L136: 1
B137: Sem nome 4 | F137: Tete | G137: Moatize | H137: Macuane Mangol | I137: Kit 1 | J137: 0 | K137: 99 | L137: 99
A138: 0506-0002 | B138: Tomás Jorge António Váz | C138: 865514026 | D138: Bernardo Xavier Jojo | E138: 865438512 | F138: Tete | G138: Moatize | I138: Kit 1 | J138: 464 | K138: 0 | L138: -464
A139: 0514-0001 | B139: Antonio Osvaldo Ausse | D139: Toto Araujo Macajo | E139: 846916018 | F139: Tete | G139: Mutarara | H139: Canhungue | I139: Kit 1 | J139: 0 | K139: 56 | L139: 56
A140: 0514-0002 | B140: Carlito Jose Angola | C140: 841484730 | D140: Toto Araujo Macajo | E140: 846916018 | F140: Tete | G140: Mutarara | H140: Vila Nova da Fronteira | I140: Kit 1 | J140: 0 | K140: 56 | L140: 56
A141: 0514-0003 | B141: Isaquel Amilcar Andate-Fanessi | D141: Toto Araujo Macajo | E141: 846916018 | F141: Tete | G141: Mutarara | H141: Inhangoma-Sede | I141: Kit 1 | J141: 0 | K141: 56 | L141: 56
A142: 0514-0004 | B142: Julio Vasco Chimica | C142: 840200222 | D142: Toto Araujo Macajo | E142: 846916018 | F142: Tete | G142: Mutarara | H142: Nhamayabwe-Sede | I142: Kit 1 | J142: 0 | K142: 56 | L142: 56
A143: 0514-0005 | B143: Meque Nhamitambo | C143: 844148631 | D143: Toto Araujo Macajo | E143: 846916018 | F143: Tete | G143: Mutarara | H143: Canámua | I143: Kit 1 | J143: 0 | K143: 56 | L143: 56
A144: 0514-0007 | B144: Pedro Benjamim Beba-Rafael | C144: 841675126 | D144: Toto Araujo Macajo | E144: 846916018 | F144: Tete | G144: Mutarara | H144: Sinjal | I144: Kit 1 | J144: 0 | K144: 56 | L144: 56
A145: 0514-0008 | B145: Santo Soares-Miceres Continho | D145: Toto Araujo Macajo | E145: 846916018 | F145: Tete | G145: Mutarara | H145: Charre-Sede | I145: Kit 1 | J145: 0 | K145: 56 | L145: 56
B146: Sem nome 2 | D146: Toto Araujo Macajo | E146: 846916018 | F146: Tete | G146: Mutarara | H146: Autarquia de Nhamayabue | I146: Kit 1 | J146: 0 | K146: 308 | L146: 308
B147: Sem nome 3 | F147: Tete | G147: Mágoè | H147: Macuane Mangol | I147: Kit 1 | J147: 0 | K147: 250 | L147: 250
A148: 0508-0005 | B148: Oliveira Felizbeto Daniel | C148: 875081383 | D148: Abdul João | E148: 867084801 | F148: Tete | G148: Zumbu | H148: Mphangula | I148: Kit 1 | J148: 0 | K148: 50 | L148: 50
A149: 0508-0006 | B149: Westen Gilberto Gimo | C149: 865514026 | D149: Abdul João | E149: 867084801 | F149: Tete | G149: Zumbu | H149: Zunbu Sede | I149: Kit 1 | J149: 0 | K149: 200 | L149: 200
A150: 0601-0009 | B150: Anifo Daudo Aboo | C150: 844821455 | D150: Arcanjo Paulino Manuel | E150: 860555190 | F150: Zambezia | G150: Alto-Molócue | H150: Derre-Sede | I150: Kit 1 | J150: 0 | K150: 2 | L150: 2
A151: 0603-0009 | B151: Anifo Daudo Aboo | C151: 844821455 | D151: Arcanjo Paulino Manuel | E151: 860555190 | F151: Zambezia | G151: Derre | H151: Derre-Sede | I151: Kit 1 | J151: 0 | K151: 10 | L151: 10
A152: 0603-0010 | B152: Chalosse B. Guidion | C152: 862873320 | D152: Arcanjo Paulino Manuel | E152: 860555190 | F152: Zambezia | G152: Derre | H152: Derre-Sede | I152: Kit 1 | J152: 0 | K152: 22 | L152: 22
A153: 0603-0011 | B153: Emilia Luciano | C153: 873478589 | D153: Arcanjo Paulino Manuel | E153: 860555190 | F153: Zambezia | G153: Derre | H153: Derre-Sede | I153: Kit 1 | J153: 0 | K153: 10 | L153: 10
A154: 0603-0012 | B154: Frederico Custavo Soares | C154: 862516431 | D154: Arcanjo Paulino Manuel | E154: 860555190 | F154: Zambezia | G154: Derre | H154: Derre-Sede | I154: Kit 1 | J154: 0 | K154: 12 | L154: 12
A155: 0603-0013 | B155: Nelita A. Alfândega | C155: 868088841 | D155: Arcanjo Paulino Manuel | E155: 860555190 | F155: Zambezia | G155: Derre | H155: Derre-Sede | I155: Kit 1 | J155: 0 | K155: 19 | L155: 19
A156: 0603-0014 | B156: Seldon J. Fortunato | C156: 879453080 | D156: Arcanjo Paulino Manuel | E156: 860555190 | F156: Zambezia | G156: Derre | H156: Derre-Sede | I156: Kit 1 | J156: 0 | K156: 29 | L156: 29
A157: 0603-0015 | B157: Suzana Mario Beirao | C157: 876840146 | D157: Arcanjo Paulino Manuel | E157: 860555190 | F157: Zambezia | G157: Derre | H157: Derre-Sede | I157: Kit 1 | J157: 0 | K157: 18 | L157: 18
A158: 0608-0008 | B158: Fernando António Sabonete | C158: 867007385 | D158: Ernesto Carlos Retxua | E158: 878543976 | F158: Zambezia | G158: Lugela | H158: Iaba | I158: Kit 1 | J158: 0 | K158: 13 | L158: 13
A159: 0608-0009 | B159: Regina da Gloria Hortencilio | C159: 861723006 | D159: Ernesto Carlos Retxua | E159: 878543976 | F159: Zambezia | G159: Lugela | H159: Ebide | I159: Kit 1 | J159: 0 | K159: 10 | L159: 10
A160: 0608-0010 | B160: Will Arcanjo Aguiar | C160: 845881970 | D160: Ernesto Carlos Retxua | E160: 878543976 | F160: Zambezia | G160: Lugela | H160: Mussengane | I160: Kit 1 | J160: 0 | K160: 2 | L160: 2
A161: 0612-0010 | B161: Zacarias Muaramussa | C161: 877479661 | D161: Atanasio Freitas Pedro | F161: Zambezia | G161: Mopeia | H161: Nzanza | I161: Kit 2 | J161: 0 | K161: 29 | L161: 29
A162: 0618-0001 | B162: Adelina Manuel Antonio | C162: 845403564/876217340 | D162: Geraldo Tarcisio Emilio | E162: 843635073/864043311 | F162: Zambezia | G162: Namacurra | H162: Pida | I162: Kit 1 | J162: 0 | K162: 93 | L162: 93
A163: 0618-0002 | B163: Alcina Manuel Mutamievo | C163: 846103695/861663298 | D163: Geraldo Tarcisio Emilio | E163: 843635073/864043311 | F163: Zambezia | G163: Namacurra | H163: Namacurra Sede | I163: Kit 2 | J163: 0 | K163: 29 | L163: 29
A164: 0618-0003 | B164: Alfredo Benjamim Lopes Fungulane | C164: 850289289/876133791 | D164: Geraldo Tarcisio Emilio | E164: 843635073/864043311 | F164: Zambezia | G164: Namacurra | H164: Mutange | I164: Kit 2 | J164: 0 | K164: 100 | L164: 100
A165: 0618-0004 | B165: Arune Hortencio Evague | C165: 842372823/870790299 | D165: Geraldo Tarcisio Emilio | E165: 843635073/864043311 | F165: Zambezia | G165: Namacurra | H165: Mexixine | I165: Kit 2 | J165: 0 | K165: 111 | L165: 111
A166: 0618-0005 | B166: Campaue Fernando Caxite | C166: 849803924/869803924 | D166: Geraldo Tarcisio Emilio | E166: 843635073/864043311 | F166: Zambezia | G166: Namacurra | H166: Muebele | I166: Kit 1 | J166: 0 | K166: 101 | L166: 101
A167: 0618-0006 | B167: Cereneu Pedro Lopes | C167: 866000902/840592752 | D167: Geraldo Tarcisio Emilio | E167: 843635073/864043311 | F167: Zambezia | G167: Namacurra | H167: Muebele | I167: Kit 1 | J167: 0 | K167: 99 | L167: 99
A168: 0618-0007 | B168: Dalmiro Armando Antonio Frasqueira | C168: 840475995/874225214 | D168: Geraldo Tarcisio Emilio | E168: 843635073/864043311 | F168: Zambezia | G168: Namacurra | H168: Malei | I168: Kit 1 | J168: 0 | K168: 48 | L168: 48
A169: 0618-0008 | B169: Esgiraque Junqueiro Mordade | C169: 840544976/872949879 | D169: Geraldo Tarcisio Emilio | E169: 843635073/864043311 | F169: Zambezia | G169: Namacurra | H169: Malei | I169: Kit 1 | J169: 0 | K169: 56 | L169: 56
A170: 0618-0009 | B170: Esteves Arlindo Evirihe Saguate | C170: 879085550/849085555 | D170: Geraldo Tarcisio Emilio | E170: 843635073/864043311 | F170: Zambezia | G170: Namacurra | H170: Malei | I170: Kit 1 | J170: 0 | K170: 38 | L170: 38
A171: 0618-0010 | B171: Francisco Rainde Csquinho | C171: 868029600/845858445 | D171: Geraldo Tarcisio Emilio | E171: 843635073/864043311 | F171: Zambezia | G171: Namacurra | H171: Mutange | I171: Kit 2 | J171: 0 | K171: 113 | L171: 113
A172: 0618-0011 | B172: Isolina Joao Mindiate | C172: 840553574/864502201 | D172: Geraldo Tarcisio Emilio | E172: 843635073/864043311 | F172: Zambezia | G172: Namacurra | H172: Pida | I172: Kit 1 | J172: 0 | K172: 92 | L172: 92
A173: 0618-0012 | B173: Lorito Ramos Ribeiro | C173: 843859261 | D173: Geraldo Tarcisio Emilio | E173: 843635073/864043311 | F173: Zambezia | G173: Namacurra | H173: Furquia | I173: Kit 1 | J173: 0 | K173: 516 | L173: 516
A174: 0618-0013 | B174: Melito Tomane José Mentiroso | C174: 842615848/864144416 | D174: Geraldo Tarcisio Emilio | E174: 843635073/864043311 | F174: Zambezia | G174: Namacurra | H174: Mbaua | I174: Kit 1 | J174: 0 | K174: 504 | L174: 504
A175: 0618-0014 | B175: Motijane Antonio Caetano | C175: 847498001/870971733 | D175: Geraldo Tarcisio Emilio | E175: 843635073/864043311 | F175: Zambezia | G175: Namacurra | H175: Macuse Sede | I175: Kit 2 | J175: 0 | K175: 151 | L175: 151
A176: 0618-0015 | B176: Nadir Joao Titos Simbine | C176: 845568288/863012212 | D176: Geraldo Tarcisio Emilio | E176: 843635073/864043311 | F176: Zambezia | G176: Namacurra | H176: Mutange | I176: Kit 2 | J176: 0 | K176: 87 | L176: 87
A177: 0618-0016 | B177: Paulino Paulo Abreu Latibo | C177: 845222813/862403639 | D177: Geraldo Tarcisio Emilio | E177: 843635073/864043311 | F177: Zambezia | G177: Namacurra | H177: Mexixine | I177: Kit 2 | J177: 0 | K177: 109 | L177: 109
A178: 0618-0017 | B178: Remigio Veloso Sebastiao | C178: 878051994 | D178: Geraldo Tarcisio Emilio | E178: 843635073/864043311 | F178: Zambezia | G178: Namacurra | H178: Namacurra Sede | I178: Kit 2 | J178: 0 | K178: 28 | L178: 28
A179: 0618-0018 | B179: Teresa Maria de Figueredo Cosmo | C179: 844101011/874101011 | D179: Geraldo Tarcisio Emilio | E179: 843635073/864043311 | F179: Zambezia | G179: Namacurra | H179: Namacurra Sede | I179: Kit 2 | J179: 0 | K179: 44 | L179: 44
A180: 0103-0012 | B180: Gércio Eduardo Cossa | C180: 862159843 | D180: Jordao Pedro | E180: 878875732 | F180: Gaza | G180: Bilene | H180: Mazivila (Olombe) | I180: Kit 1 | J180: 0 | K180: 16 | L180: 16
A181: 0103-0013 | B181: Gércio Eduardo Cossa | C181: 862159843 | D181: Jordao Pedro | E181: 878875732 | F181: Gaza | G181: Bilene | H181: Mazivila (Olombe) | I181: Kit 2 | J181: 0 | K181: 0 | L181: 0
A182: 0103-0018 | B182: Jordao Pedro | C182: 878875732 | D182: Jordao Pedro | E182: 878875732 | F182: Gaza | G182: Bilene | H182: Incaia Sede | I182: Kit 1 | J182: 0 | K182: 16 | L182: 16
A183: 0103-0014 | B183: Moisés Chirunguze | C183: 845243130 | D183: Jordao Pedro | E183: 878875732 | F183: Gaza | G183: Bilene | H183: Messano (Fulane) | I183: Kit 1 | J183: 0 | K183: 16 | L183: 16
A184: 0103-0015 | B184: Moisés Chirunguze | C184: 845243130 | D184: Jordao Pedro | E184: 878875732 | F184: Gaza | G184: Bilene | H184: Messano (Fulane) | I184: Kit 2 | J184: 0 | K184: 0 | L184: 0
A185: 0104-0012 | B185: Neisma Jotamo Chilaule | C185: 870936440 | D185: Neisma Jotamo Chilaule | E185: 870936440 | F185: Gaza | G185: Chibuto | H185: Alto Changane-Chivive | I185: Kit 1 | K185: 737
A186: 0105-0003 | B186: Selsso Henriques Munguambe | C186: 876699192 | D186: Selsso Henriques Munguambe | E186: 876699192 | F186: Gaza | G186: Chicualacuala | H186: Chicorro | I186: Kit 1 | K186: 140
A187: 0101-0007 | B187: Dolver Jose Manuel | C187: 877002151 | D187: Dolver Jose Manuel | E187: 877002151 | F187: Gaza | G187: Chigubo | H187: Ndindiza | I187: Kit 1 | J187: 0 | K187: 40 | L187: 40
A188: 0102-0005 | B188: Anselmo Rosita Mambo | C188: 867575426 | D188: Anselmo Rosita Mambo | E188: 867575426 | F188: Gaza | G188: Chongoene | H188: Nhancutse | I188: Kit 2
A189: 0106-0014 | B189: Alfredo Mathe | C189: 869940220 | D189: Nelson David Novela | E189: 868733522 | F189: Gaza | G189: Chókwè | H189: Posto Sede Chokwe | I189: Kit 1 | J189: 37 | K189: 1525 | L189: 1488
A190: 0106-0014 | B190: Alfredo Mathe | C190: 869940220 | D190: Nelson David Novela | E190: 868733522 | F190: Gaza | G190: Chókwè | H190: Posto Sede Chokwe | I190: Kit 2 | J190: 13 | K190: 607 | L190: 594
A191: 0106-0015 | B191: Nelson David Novela | C191: 868733522 | D191: Nelson David Novela | E191: 868733522 | F191: Gaza | G191: Chókwè | H191: Todo o Dsitrito | I191: Kit 2 | J191: 91 | K191: 747 | L191: 656
A192: 0107-0008 | B192: Dercio Victor Tenda | C192: 862259677 | D192: Dercio Victor Tenda | E192: 862259677 | F192: Gaza | G192: Guija | H192: Caniçado | I192: Kit 1 | K192: 364
A193: 0108-0016 | B193: Armando Manuel Ussivane | C193: 864272425 | D193: Armando Manuel Ussivane | E193: 864272425 | F193: Gaza | G193: Limpopo | H193: Chicumbane Sede | I193: Kit 2 | J193: 0 | K193: 92 | L193: 92
A194: 0108-0006 | B194: Fátima Tomás Zavala | C194: 877129346 | D194: Armando Manuel Ussivane | E194: 864272425 | F194: Gaza | G194: Limpopo | H194: Julios Nherere | I194: Kit 1 | J194: 1830 | K194: 76 | L194: -1754
A195: 0108-0006 | B195: Fátima Tomás Zavala | C195: 877129346 | D195: Armando Manuel Ussivane | E195: 864272425 | F195: Gaza | G195: Limpopo | H195: Julios Nherere | I195: Kit 2 | J195: 0 | K195: 2992 | L195: 2992
A196: 0108-0015 | B196: Jorge Tamele | D196: Armando Manuel Ussivane | E196: 864272425 | F196: Gaza | G196: Limpopo | H196: Chicumbane Sede | I196: Kit 1 | J196: 0 | K196: 321 | L196: 321
A197: 0109-0010 | B197: Jose Alberto Macaringue | C197: 861798330 | D197: Jose Alberto Macaringue | E197: 861798330 | F197: Gaza | G197: Mabalane | H197: Chimunhuane | I197: Kit 1 | K197: 200
A198: 0110-0006 | B198: Almirante Joao Almirante | C198: 868943410 | D198: Olimpio Bila | E198: 873911284 | F198: Gaza | G198: Mandlakazi | H198: Bandze | I198: Kit 1 | J198: 0 | K198: 21 | L198: 21
A199: 0110-0007 | B199: Almirante Joao Almirante | C199: 868943410 | D199: Olimpio Bila | E199: 873911284 | F199: Gaza | G199: Mandlakazi | H199: Bandze | I199: Kit 2 | J199: 0 | K199: 14 | L199: 14
A200: 0110-0008 | B200: Celso Jose Mbalate | D200: Olimpio Bila | E200: 873911284 | F200: Gaza | G200: Mandlakazi | I200: Kit 1 | J200: 0 | K200: 21 | L200: 21
A201: 0110-0009 | B201: Celso Jose Mbalate | D201: Olimpio Bila | E201: 873911284 | F201: Gaza | G201: Mandlakazi | I201: Kit 2 | J201: 0 | K201: 14 | L201: 14
A202: 0110-0010 | B202: Ermelinda Bento Mugabe | D202: Olimpio Bila | E202: 873911284 | F202: Gaza | G202: Mandlakazi | I202: Kit 1 | J202: 0 | K202: 21 | L202: 21
...

Sheet Composição dos Kits
A1: Composição dos Kits de Emergência
A3: Insumo | B3: Unidade | C3: Kit 1 (por família) | D3: Kit 2 (por família) | E3: Observação
A4: Milho | B4: Kg | C4: 12.5 | D4: 0 | E4: Apenas no Kit 1
A5: Arroz | B5: Kg | C5: 0 | D5: 50 | E5: Apenas no Kit 2
A6: Feijão Vulgar | B6: Kg | C6: 15 | D6: 15 | E6: Presente em ambos
A7: Couve | B7: g | C7: 10 | D7: 10 | E7: Sementes
A8: Alface | B8: g | C8: 10 | D8: 10 | E8: Sementes
A9: NPK 12.24.12 | B9: Kg | C9: 50 | D9: 50 | E9: Fertilizante
A10: Enxada | B10: un | C10: 1 | D10: 1 | E10: Ferramenta
A11: Emamectim Benzoato | B11: L | C11: 0.5 | D11: 0.5 | E11: Insecticida (ambos)
A12: Imidacloprid | B12: L | C12: 0.5 | D12: 0 | E12: Apenas no Kit 1
A13: MCPA | B13: L | C13: 0 | D13: 1.5 | E13: Apenas no Kit 2 (herbicida)
